Workbook
Name HoldingInstitution: StaticData!$C$1:$C$21
Name InstitutionName: StaticData!$B$1:$B$1457
Name ProjectAcronym: StaticData!$D$1:$D$225
Name SiteName: StaticData!$E$1:$E$24
Name TaxonScientificName: StaticData!$A$1:$A$5470

Sheet README
A1: GnpISVersionNumber | B1: 14_1
A2: StaticDataExtraction
A3: SubmissionType | B3: Ephesis
A5: This worksheet is used for submit phenotyping data.
A7: SUBMIT NOTE | B7: RED names indicate fields / sheets required for submission, must not be empty.
B8: BLACK names indicate fields / sheets that are optional for submission, may be empty.
B9: BLUE names indicate specific fields / sheets for submission. Column can be empty but must not be deleted.
A11: DOCUMENTATION
A14: TRIAL | B14: General information on the trial
B15: TrialName | C15: TrialCode | D15: DateBegin | E15: DateEnd | F15: TrialGoal | G15: TrialComments | H15: PhenotypingCampain | I15: PMID | J15: X | K15: Y | L15: PreviousCrop | M15: TrialDesign | N15: TrialHistory | O15: ProjectAcronym | P15: TrialSet | Q15: TrialSetType
A16: Description | B16: Rapsodyn SYN 16 | C16: RAPSO_SYN | D16: 42039 | E16: 41855 | F16: Diversity analysis and adaptation to N constraints | G16: Visual differences between N regimes ; troubles at harvest | H16: 2015-2016 | J16: row | K16: culumn | L16: wheat | M16: RCB | O16: Rapsodyn
A17: Example | B17: mon test | C17: MON_TEST | D17: 22/03/2013 | E17: 2014 | F17: Diversity analysis | G17: Essai test | H17: 2012 | I17: 15608279,2052071 | J17: row | K17: column | N17: Come from BORDEAUX (Louvet) | P17: myGroup | Q17: Replication
A18: Data type | B18: String | C18: String | D18: Date: dd/mm/yyyy Date: mm/yyyy Date: yyyy | E18: Date: dd/mm/yyyy Date: mm/yyyy Date: yyyy | F18: String | G18: String | H18: String | I18: Number | J18: String | K18: String | L18: String | M18: String | N18: String | O18: String | P18: String | Q18: String
A21: SITE | B21: General information on the experimental site
B22: SiteName | C22: Latitude | D22: Longitude | E22: Elevation | F22: Exposure | G22: Slope | H22: CityOrRegionOrCountry | I22: SiteStatus | J22: Landowner | K22: Comment | L22: MeteoStationCode | M22: MeteoStationNetwork
A23: Description | B23: Syngenta Verpillières, 80 | C23: 49.6692 | D23: 2.822858 | E23: 79 | G23: NONE | H23: VER | I23: P
A24: Examples | B24: Bordeaux | H24: FRA | I24: S | J24: Forêt domaniale
A25: Data type | B25: String | C25: Number | D25: Number | E25: Number | F25: String | G25: String | H25: String | I25: P (= Private property) I (= INRA) S (= Under a specific regime) | J25: String | K25: String | L25: String | M25: String
A28: CONTACT | B28: List of persons involved in this trial (scientific, submiter, landowner…)
B29: Type | C29: LastName | D29: FirstName | E29: Phone | F29: Fax | G29: Email | H29: Institution | I29: Laboratory
A30: Description | B30: Submiter | C30: MOREAU | D30: Julien | E30: +33 (0) 6 78 15 40 47 | G30: julien.moreau@syngenta.com | H30: Syngenta France SAS | I30: AUREA
A31: Examples | B31: Submiter | C31: DUPOND | D31: Jacques | E31: +33 (0) 1 30 83 38 99 | F31: +33 (0) 1 30 83 38 90 | G31: jacques.dupond@email.com | H31: INRA | I31: URGI
A32: Data type | B32: String | C32: String | D32: String | E32: Phone number | F32: Fax number | G32: String | H32: String | I32: String
A35: VARIABLE | B35: List of variables observed in this trial. Idealy they are part of a well identified ontology.
B36: Each variable is reused as a column in the Data sheet.
B37: OntologyName | C37: VariableCode | D37: VariableName | E37: Description | F37: MeasurmentUnit | G37: MeasurmentProtocol | H37: ParentVariable | I37: Comment
A38: Description | B38: Full name of the ontology holding this variable | C38: Identification of the variable. Unique within the ontology declared in OntologyName. This code is used as header in the Data sheet | D38: Name of the variable | E38: Full description of the variable | F38: Unit of the mesured variable | G38: Reference measurment protocol of the variable | H38: VariableCode of this variable's parent | I38: Comments on the variable
A39: Examples | B39: trait ontology | C39: haut | D39: hauteur | F39: cm
A40: Data type | B40: String | C40: String | D40: String | E40: String | F40: String | G40: String | H40: String | I40: String
A43: PLANT MATERIAL | B43: List of genotypes. Should be preexisting in GnpIS. If not sure contact us.
B44: TaxonScientificName | C44: AccessionNumber | D44: AccessionName | E44: HoldingInstitution | F44: LotName
A45: Description | B45: Scientific name of the taxon | C45: Unique identification of the accession/genotype | D45: Full name of the accession | E45: Institution holding this accession | F45: Identification of the physical plant(s) used in the trial : seeds, tree, …. Used in the first column of the Data sheet
A46: Examples | B46: Triticum aestivum | C46: 274Col49 | D46: chargeur | F46: ch
A47: Data type | B47: String | C47: String | D47: String | E47: String | F47: String
A50: TREATMENT | B50: List of factor and modalities used in this trial. Treatments are combination of modalities.
B51: Each factor is reused as a column in the Data sheet. The modalities of each factor are the authorised value for this factor/column.
B52: Factor | C52: ModeCode | D52: ModeName | E52: ModeDescription
A53: Description | B53: Name of the factor. This name is used as header in the Data sheet | C53: Unique identifier of the modality. This code is used as value in the Data sheet factor's column | D53: Full name of the modality | E53: Full description of the modality, possibly with a short description of its caracteristics like phenologic stade for a given treatment
A54: Examples | B54: engrais | C54: N0 | D54: azote 0 | E54: ajout de 0 kilog/hectar de produitA a x concentration tous les mois.
A55: Data type | B55: String | C55: String | D55: String | E55: String
A58: LEVEL | B58: Structure of the trial, for instance bloc > plot > plant. Can be empty if you want to store only genotype x factor data and no plot data.
B59: Each level is reused as a column in the Data sheet.
B60: Code | C60: Name | D60: Description | E60: ParentLevel
A61: Description | B61: Unique identification of the level (plot, bloc, plant, …) within the trial. This code is used as header in the Data sheet | C61: Full name of the level | D61: Description of the level | E61: Code of this level parents. If you have X levels, this column must be filled for X-1 levels
A62: Examples | B62: Rep | C62: Repetition
B63: Bloc | C63: Bloc | E63: Rep
A64: Data type | B64: String | C64: String | D64: String | E64: String
A67: DATA | B67: Data matrix: hold any type of observation (phenotype, env, etc…)
B68: LotName | C68: <factors> | D68: <levels> | E68: X | F68: Y | G68: X(m) | H68: Y(m) | I68: <variables>_value | J68: <variables>_date
A69: Description | B69: Identification of the genotype of the observed object. Must be found in the VarietalList sheet | C69: headers: all factors declared in the Treatments sheet | D69: headers: all levels declared in the StudySubjectLevels sheet | E69: X position of the observed object | F69: Y position of the observed object | G69: X position of the observed object in meters | H69: Y position of the observed object in meters | I69: headers: all variables declared in the Variables sheet | J69: headers: all variables declared in the Variables sheet
C70: values: all mode_code declared in the Treatment sheet | D70: values: levels identifiers | I70: values: value of the variable for the observed object | J70: values: observation date of the variable
A71: Examples | B71: ch | C71: header: engrais value: N0 | D71: header: bloc value: bloc1 | E71: 1 | F71: 3 | I71: header: haut_value value: 15 | J71: header: haut_date value:
A72: Data type | B72: String | C72: String | D72: String | E72: String | F72: String | G72: Number | H72: Number | I72: String or Number | J72: Date
A75: FILES
B76: FileName | C76: Link | D76: FileType | E76: FileSize | F76: CreationDate | G76: Description
A77: Description | B77: Name of the file | C77: URL where the file can be found (file repository) | D77: File type | E77: File size | F77: Creation date of the file | G77: Description of the file
A78: Example | B78: MeteoWholeTrial.txt ITK.xls Plan.xls | C78: http://urgi.versailles.inra.fr/Species/Wheat/Sequence-Repository | D78: xls | E78: 39 | F78: 40568
A79: Data type | B79: String | C79: String | D79: xls csv txt | E79: Number | F79: Date: dd/mm/yyyy | G79: String
A82: FOREST COMPLEMENTARY INFO | B82: Additional fields. Mandatory tab for forest submissions.
B83: TrialType | C83: TrialStatus | D83: DataFormat
A84: Description | B84: Type of this trial | C84: State and monitoring level of this trial | D84: Which format is used to store the data ?
A85: Examples | B85: 1 | C85: 3 | D85: Digital
A86: Data type | B86: 1 (= provenances comparison) 2 (= maternal descendants comparison) 3 (= two-parents descendants comparison) 4 (= species comparison) 5 (=clones seeds orchard) 6 (=clonal comparison) 7 (= clonal park) 8 (= juveniles comparison) 9 (= other) | C86: A (= abandoned/ruined) 1 (= weakly active) 2 (= moderately active) 3 (= active) 4 (= very active) 9 (= unknown) | D86: Paper Scan Digital Unknown

Sheet Trial
A1: TrialName | B1: TrialCode | C1: DateBegin | D1: DateEnd | E1: TrialGoal | F1: TrialComments | G1: PhenotypingCampain | H1: PMID | I1: X | J1: Y | K1: PreviousCrop | L1: TrialDesign | M1: TrialHistory | N1: ProjectAcronym | O1: TrialSet | P1: TrialSetType
A2: Rapsodyn SYN 16 | B2: RAPSO_SYN | C2: 42039 | D2: 41855 | E2: Diversity analysis and adaptation to N constraints | F2: Visual differences between N regimes ; troubles at harvest | G2: 2015-2016 | I2: row | J2: column | K2: winter wheat | L2: RCB | N2: Rapsodyn

Sheet Site
A1: SiteName | B1: Latitude | C1: Longitude | D1: Elevation | E1: Exposure | F1: Slope | G1: CityOrRegionOrCountry | H1: SiteStatus | I1: Landowner | J1: Comment | K1: MeteoStationCode | L1: MeteoStationNetwork
A2: Syngenta Verpillières, 80 | B2: 49.6692 | C2: 2.822858 | D2: 79 | F2: NONE | G2: VER | H2: P

Sheet Contact
A1: Type | B1: LastName | C1: FirstName | D1: Phone | E1: Fax | F1: Email | G1: Institution | H1: Laboratory
A2: Submitter | B2: MOREAU | C2: Julien | D2: +33 (0) 6 78 15 40 47 | F2: julien.moreau@syngenta.com | G2: Syngenta France SAS | H2: AUREA

Sheet Variable
A1: OntologyName | B1: VariableCode | C1: VariableName | D1: Description | E1: MeasurmentUnit | F1: MeasurmentProtocol | G1: ParentVariable | H1: Comment
A2: INRA Brassica Experimental Ontology | B2: PLANTDENS | C2: Plant_Density | D2: Number of viable plants counted per surface unit. | E2: Plant nb.m-² | F2: Count the number of plants on linear sections defined in each sowing line at the exception of the border lines. PLANTDENS = (Total nb of plants counted) / (Ls x Nc x E). Where Ls = length of a linear section in m (1 m or more when plant density is variable within a plot), Nc = nb of sowing lines chosen for plant counting, E = inter-line spacing.
A3: INRA Brassica Experimental Ontology | B3: PLOTHARVEST | C3: Plot_Harvest_Weight | D3: Weight (kg) of raw materials harvested by plot. | E3: kg | F3: A measurement of the amount (in kg) of raw material that was harvested per plot as determined by on-board weighing on the harvester.
A4: INRA Brassica Experimental Ontology | B4: OY | C4: Oil_Yield | D4: Oil yield per ha. | E4: q.ha-1 | F4: OY = (O x SY)
A5: INRA Brassica Experimental Ontology | B5: PLOTSURF | C5: Plot_Surface | D5: Surface of the elementary experimental plot. | E5: m2 | F5: Surface is determined by the experimental design. PLOTSURF = L x N x E. Where L = length of the sowing line, N = Nb of sowing lines, E = inter-line spacing.
A6: INRA Brassica Experimental Ontology | B6: PrY | C6: Prot_Yield | D6: Protein yield per ha. | E6: q.ha-1 | F6: PrY = (Pr x SY)
A7: INRA Brassica Experimental Ontology | B7: SN | C7: Seed_Nb_Surface | D7: Number of seeds per square meter. | E7: Seed nb.m-² | F7: SN = (SY / TSW) x 10000
A8: INRA Brassica Experimental Ontology | B8: SYNORM | C8: Seed_Yield_Normalized_q/ha | D8: Weight (q) of seeds that was harvested per ha with moisture and impurity contents standardized with commercial values at 9% (SEEDH2ONorm) and 2% (SEEDIMPURNorm) respectively. | E8: q.ha-1 | F8: SYNORM = (PLOTHARVEST / PLOTSURF) x (((100 - SEEDH2O_HARV or LAB)/(100 - SEEDH2ONorm)) x ((100 - SEEDIMPUR)/(100 - SEEDIMPURNorm))) x 100
A9: INRA Brassica Experimental Ontology | B9: PLANTSIZE | C9: Plant_Size | D9: Height of plants in an experimental plot. | E9: cm | F9: Height is measured from ground to the top of the plants using a dipstick graduated in cm.
A10: INRA Brassica Experimental Ontology | B10: ERUCIC | C10: Erucic_Acid | D10: Content of erucic acid in seeds determined by NIRS. | E10: % total fatty acids | F10: NIRS assay. XXX calibration.
A11: INRA Brassica Experimental Ontology | B11: PALMITIC | C11: Palmitic_Acid | D11: Content of palmitic acid in seeds determined by NIRS. | E11: % total fatty acids | F11: NIRS assay. XXX calibration.
A12: INRA Brassica Experimental Ontology | B12: STEARIC | C12: Stearic_Acid | D12: Content of stearic acid in seeds determined by NIRS. | E12: % total fatty acids | F12: NIRS assay. XXX calibration.
A13: INRA Brassica Experimental Ontology | B13: OLEIC | C13: Oleic_Acid | D13: Content of oleic acid in seeds determined by NIRS. | E13: % total fatty acids | F13: NIRS assay. XXX calibration.
... A27: INRA Brassica Experimental Ontology | B27: LODGING | C27: Plant_Lodging | D27: Scoring of the plant lodging of the plot. | E27: Note | F27: Visual notation is attributed to the plants for each plot, taking into account the surface and the intensity of lodging LODGING = 0 : NA 1 : No lodging 2 : Culture leaning, without impact 5 : Average loding, low impact 7 : High lodging, serious impact 9 : Total lodging, compromised harvest

Sheet PlantMaterial
A1: TaxonScientificName | B1: AccessionNumber | C1: AccessionName | D1: HoldingInstitution | E1: LotName
A2: Brassica napus L. | B2: 1 | C2: AVISO | E2: 1 | F2: A modifier si nécessaire
A3: Brassica napus L. | B3: 3 | C3: MONTEGO | E3: 3
A4: Brassica napus L. | B4: 5 | C4: TENOR | E4: 5
A5: Brassica napus L. | B5: 7 | C5: EXPRESS | E5: 7
A6: Brassica napus L. | B6: 12 | C6: AVISO | E6: 12
A7: Brassica napus L. | B7: 14 | C7: MONTEGO | E7: 14
A8: Brassica napus L. | B8: 16 | C8: TENOR | E8: 16
A9: Brassica napus L. | B9: 18 | C9: EXPRESS | E9: 18
A10: Brassica napus L. | B10: 23 | C10: AVISO | E10: 23
A11: Brassica napus L. | B11: 25 | C11: MONTEGO | E11: 25
A12: Brassica napus L. | B12: 27 | C12: TENOR | E12: 27
A13: Brassica napus L. | B13: 29 | C13: EXPRESS | E13: 29
A14: Brassica napus L. | B14: 2 | C14: A05-AMQ0 | E14: 2
... A22: Brassica napus L. | B22: 15 | C22: DK038 | E22: 15
A23: Brassica napus L. | B23: 17 | C23: EXL4816 | D23: Euralis | E23: 17
A24: Brassica napus L. | B24: 19 | C24: EXL3155 | D24: Euralis | E24: 19
A25: Brassica napus L. | B25: 20 | C25: C03-1ESQ0 | D25: Euralis | E25: 20
A26: Brassica napus L. | B26: 21 | C26: C03-1ESQ1 | D26: Euralis | E26: 21
A27: Brassica napus L. | B27: 22 | C27: C04-1ESQ0 | D27: Euralis | E27: 22
A28: Brassica napus L. | B28: 24 | C28: C04-1ESQ1 | D28: Euralis | E28: 24
A29: Brassica napus L. | B29: 26 | C29: RAPSO_304 | D29: Limagrain | E29: 26
A30: Brassica napus L. | B30: 28 | C30: LEL17 | D30: Limagrain | E30: 28
A31: Brassica napus L. | B31: 30 | C31: C04-1LEQ0 | D31: Limagrain | E31: 30
A32: Brassica napus L. | B32: 31 | C32: C04-1LEQ1 | D32: Limagrain | E32: 31
A33: Brassica napus L. | B33: 32 | C33: A05-1LEQ0 | D33: Limagrain | E33: 32
A34: Brassica napus L. | B34: 33 | C34: A05-1LEQ1 | D34: Limagrain | E34: 33
... A43: Brassica napus L. | B43: 42 | C43: C04-1SYNQ1 | D43: Syngenta | E43: 42

Sheet Treatment
A1: Factor | B1: ModeCode | C1: ModeName | D1: ModeDescription
A2: Azote | B2: N- | C2: azote limitant | D2: Fertilisation limitante (Dose)
A3: Azote | B3: N+ | C3: azote optimal | D3: Fertilisation optimale (Dose)

Sheet Level
A1: Code | B1: Name | C1: Description | D1: ParentLevel
A2: bloc | B2: bloc | C2: replication
A3: plot | B3: parcelle | D3: bloc

Sheet Data
A1: LotName | B1: LotName | C1: engrais | D1: Bloc | E1: Parcelle | F1: X | G1: Y | H1: Y(m) | I1: PLANTDENS_value | J1: PLANTDENS_date | K1: REGSTAND_value | L1: REGSTAND_date | M1: PLOTHARVEST_value | N1: PLOTHARVEST_date | O1: HI_value | P1: HI_date | Q1: NHI_value | R1: NHI_date | S1: OY_value | T1: OY_date | U1: PLOTSURF_value | V1: PLOTSURF_date | W1: PODSHAT_value | X1: PODSHAT_date | Y1: PrY_value | Z1: PrY_date | AA1: SN_value | AB1: SN_date | AC1: SY_value | AD1: SY-date | AE1: SYNORM_value | AF1: SYNORM_date | AG1: TSW_value | AH1: TSW_date | AI1: PLANTSIZE_value | AJ1: PLANTSIZE_date | AK1: GRWSTG_C1_value | AL1: GRWSTG_C1_date | AM1: GRWSTG_F1_value | AN1: GRWSTG_F1_date | AO1: GRWSTG_F2_value | AP1: GRWSTG_F2_date | AQ1: GRWSTG_FLO_value | AR1: GRWSTG_FLO_date | AS1: GRWSTG_ENDFLO_value | AT1: GRWSTG_ENDFLO_date | AU1: GRWSTG_G1_value | AV1: GRWSTG_G1_date | AW1: GRWSTG_G4_value | AX1: GRWSTG_G4_date | AY1: GRWSTG_PODDEV_value | AZ1: GRWSTG_PODDEV_date | BA1: GRWSTG_G5_value | BB1: GRWSTG_G5_date | BC1: GRWSTG_PODMATURITY_value | BD1: GRWSTG_PODMATURITY_date | BE1: EMERG_value | BF1: EMERG_date | BG1: ERUCIC_value | BH1: ERUCIC_date | BI1: PALMITIC_value | BJ1: PALMITIC-date | BK1: STEARIC_value | BL1: STEARIC_date | BM1: OLEIC_value | BN1: OLEIC_date | BO1: LINOLEIC_value | BP1: LINOLEIC_date | BQ1: LINOLENIC_value | BR1: LINOLENIC_date | BS1: O_value | BT1: O_date | BU1: Pr_value | BV1: Pr_date | BW1: GLS_value | BX1: GLS_date | BY1: SEEDH2O_NIRS_value | BZ1: SEEDH2O_NIRS_date | CA1: PRMEAL_value | CB1: PRMEAL_date | CC1: SEEDH2O_HARV_value | CD1: SEEDH2O_HARV_date | CE1: SEEDH2O_LAB_value | CF1: SEEDH2O_LAB_date | CG1: SEEDIMPUR_value | CH1: SEEDIMPUR_date | CI1: BIOTIC | CJ1: CROP | CK1: CLIMATIC | CL1: LODGING_value | CM1: LODGING_date
A2: 1 | B2: =VLOOKUP(A2,PlantMaterial!B:C,2,0) -> AVISO | C2: N+ | D2: 1 | E2: used for INN | F2: 1 | G2: 1 | H2: 10.5 | I2: 37 | J2: 42430 | M2: 3.24 | N2: 42586 | S2: 9.46 | T2: 42592 | U2: 13.5 | V2: 42586 | Y2: 4.49064 | Z2: 42592 | AA2: 45 | AB2: 42249 | AE2: 23.76 | AF2: 42586 | AI2: 140 | AJ2: 42507 | AK2: 9.9 | BG2: -7.2 | BH2: 42592 | BM2: 59.6 | BN2: 42592 | BQ2: 12.2 | BR2: 42592 | BS2: 43.736264 | BT2: 42592 | BU2: 20.769231 | BV2: 42592 | BW2: 18.351648 | BX2: 42592 | CA2: 36.8 | CB2: 42592
A3: 2 | B3: =VLOOKUP(A3,PlantMaterial!B:C,2,0) -> A05-AMQ0 | C3: N+ | D3: 1 | E3: 04535 | F3: 2 | G3: 1 | H3: 10.5 | M3: 3.37 | N3: 42586 | S3: 10.41 | T3: 42592 | U3: 13.5 | V3: 42586 | Y3: 4.43383 | Z3: 42592 | AA3: 45 | AB3: 42249 | AE3: 24.77 | AF3: 42586 | AI3: 140 | AJ3: 42507 | AK3: 9.7 | BG3: -8.3 | BH3: 42592 | BM3: 60.6 | BN3: 42592 | BQ3: 11.3 | BR3: 42592 | BS3: 46.153846 | BT3: 42592 | BU3: 19.67033 | BV3: 42592 | BW3: 15.274725 | BX3: 42592 | CA3: 36.5 | CB3: 42592
A4: 3 | B4: =VLOOKUP(A4,PlantMaterial!B:C,2,0) -> MONTEGO | C4: N+ | D4: 1 | E4: used for INN | F4: 3 | G4: 1 | H4: 10.5 | M4: 2.77 | N4: 42586 | S4: 8.39 | T4: 42592 | U4: 13.5 | V4: 42586 | Y4: 3.79068 | Z4: 42592 | AA4: 45 | AB4: 42249 | AE4: 20.38 | AF4: 42586 | AI4: 130 | AJ4: 42507 | AK4: 9.6 | BG4: -8.2 | BH4: 42592 | BM4: 61.2 | BN4: 42592 | BQ4: 11.3 | BR4: 42592 | BS4: 45.274725 | BT4: 42592 | BU4: 20.43956 | BV4: 42592 | BW4: 15.164835 | BX4: 42592 | CA4: 37.4 | CB4: 42592
A5: 4 | B5: =VLOOKUP(A5,PlantMaterial!B:C,2,0) -> A05-AMQ1 | C5: N+ | D5: 1 | E5: 04537 | F5: 4 | G5: 1 | H5: 10.5 | M5: 2.77 | N5: 42586 | S5: 8.38 | T5: 42592 | U5: 13.5 | V5: 42586 | Y5: 3.81667 | Z5: 42592 | AA5: 45 | AB5: 42249 | AE5: 20.41 | AF5: 42586 | AI5: 130 | AJ5: 42507 | AK5: 9.5 | BG5: -9.6 | BH5: 42592 | BM5: 60 | BN5: 42592 | BQ5: 11.9 | BR5: 42592 | BS5: 45.164835 | BT5: 42592 | BU5: 20.549451 | BV5: 42592 | BW5: 16.373626 | BX5: 42592 | CA5: 37.5 | CB5: 42592
A6: 5 | B6: =VLOOKUP(A6,PlantMaterial!B:C,2,0) -> TENOR | C6: N+ | D6: 1 | E6: used for INN | F6: 5 | G6: 1 | H6: 10.5 | M6: 3.02 | N6: 42586 | S6: 9.12 | T6: 42592 | U6: 13.5 | V6: 42586 | Y6: 4.06809 | Z6: 42592 | AA6: 45 | AB6: 42249 | AE6: 22.23 | AF6: 42586 | AI6: 130 | AJ6: 42507 | AK6: 9.6 | BG6: -6.5 | BH6: 42592 | BM6: 59.4 | BN6: 42592 | BQ6: 11.8 | BR6: 42592 | BS6: 45.164835 | BT6: 42592 | BU6: 20.10989 | BV6: 42592 | BW6: 16.263736 | BX6: 42592 | CA6: 36.6 | CB6: 42592
A7: 6 | B7: =VLOOKUP(A7,PlantMaterial!B:C,2,0) -> C03-AMQ0 | C7: N+ | D7: 1 | E7: 04539 | F7: 6 | G7: 1 | H7: 10.5 | M7: 2.92 | N7: 42586 | S7: 8.81 | T7: 42592 | U7: 13.5 | V7: 42586 | Y7: 3.91118 | Z7: 42592 | AA7: 45 | AB7: 42249 | AE7: 21.49 | AF7: 42586 | AI7: 130 | AJ7: 42507 | AK7: 9.6 | BG7: -7.9 | BH7: 42592 | BM7: 61.6 | BN7: 42592 | BQ7: 11.7 | BR7: 42592 | BS7: 45.054945 | BT7: 42592 | BU7: 20 | BV7: 42592 | BW7: 14.505495 | BX7: 42592 | CA7: 36.4 | CB7: 42592
A8: 7 | B8: =VLOOKUP(A8,PlantMaterial!B:C,2,0) -> EXPRESS | C8: N+ | D8: 1 | E8: used for INN | F8: 6 | G8: 2 | H8: 21 | M8: 2.05 | N8: 42586 | S8: 6.09 | T8: 42592 | U8: 13.5 | V8: 42586 | Y8: 2.85 | Z8: 42592 | AA8: 45 | AB8: 42249 | AE8: 15 | AF8: 42586 | AI8: 125 | AJ8: 42507 | AK8: 10.1 | BG8: -6.9 | BH8: 42592 | BM8: 60.5 | BN8: 42592 | BQ8: 11.1 | BR8: 42592 | BS8: 44.615385 | BT8: 42592 | BU8: 20.879121 | BV8: 42592 | BW8: 17.582418 | BX8: 42592 | CA8: 37.7 | CB8: 42592
A9: 8 | B9: =VLOOKUP(A9,PlantMaterial!B:C,2,0) -> C03-AMQ1 | C9: N+ | D9: 1 | E9: 04541 | F9: 5 | G9: 2 | H9: 21 | M9: 2.78 | N9: 42586 | S9: 8.54 | T9: 42592 | U9: 13.5 | V9: 42586 | Y9: 3.7219 | Z9: 42592 | AA9: 45 | AB9: 42249 | AE9: 20.45 | AF9: 42586 | AI9: 130 | AJ9: 42507 | AK9: 9.6 | BG9: -8.4 | BH9: 42592 | BM9: 59.9 | BN9: 42592 | BQ9: 11.8 | BR9: 42592 | BS9: 45.934066 | BT9: 42592 | BU9: 20 | BV9: 42592 | BW9: 16.043956 | BX9: 42592 | CA9: 36.9 | CB9: 42592
A10: 9 | B10: =VLOOKUP(A10,PlantMaterial!B:C,2,0) -> C04-DKQ0 | C10: N+ | D10: 1 | E10: 04542 | F10: 4 | G10: 2 | H10: 21 | M10: 2.61 | N10: 42586 | S10: 8.01 | T10: 42592 | U10: 13.5 | V10: 42586 | Y10: 3.49986 | Z10: 42592 | AA10: 45 | AB10: 42249 | AE10: 19.23 | AF10: 42586 | AI10: 130 | AJ10: 42507 | AK10: 9.5 | BG10: -8.4 | BH10: 42592 | BM10: 59.4 | BN10: 42592 | BQ10: 11.8 | BR10: 42592 | BS10: 45.824176 | BT10: 42592 | BU10: 20 | BV10: 42592 | BW10: 16.923077 | BX10: 42592 | CA10: 36.8 | CB10: 42592
A11: 10 | B11: =VLOOKUP(A11,PlantMaterial!B:C,2,0) -> C04-DKQ1 | C11: N+ | D11: 1 | E11: 04543 | F11: 3 | G11: 2 | H11: 21 | M11: 2.55 | N11: 42586 | S11: 7.9 | T11: 42592 | U11: 13.5 | V11: 42586 | Y11: 3.3822 | Z11: 42592 | AA11: 45 | AB11: 42249 | AE11: 18.79 | AF11: 42586 | AI11: 130 | AJ11: 42507 | AK11: 9.5 | BG11: -8.4 | BH11: 42592 | BM11: 61.1 | BN11: 42592 | BQ11: 10.7 | BR11: 42592 | BS11: 46.153846 | BT11: 42592 | BU11: 19.78022 | BV11: 42592 | BW11: 15.604396 | BX11: 42592 | CA11: 36.7 | CB11: 42592
A12: 11 | B12: =VLOOKUP(A12,PlantMaterial!B:C,2,0) -> AM087 | C12: N+ | D12: 1 | E12: 04544 | F12: 2 | G12: 2 | H12: 21 | M12: 4 | N12: 42586 | S12: 11.96 | T12: 42592 | U12: 13.5 | V12: 42586 | Y12: 5.36373 | Z12: 42592 | AA12: 45 | AB12: 42249 | AE12: 29.31 | AF12: 42586 | AI12: 130 | AJ12: 42507 | AK12: 10 | BG12: -9.2 | BH12: 42592 | BM12: 59.8 | BN12: 42592 | BQ12: 11.2 | BR12: 42592 | BS12: 44.835165 | BT12: 42592 | BU12: 20.10989 | BV12: 42592 | BW12: 16.373626 | BX12: 42592 | CA12: 36.4 | CB12: 42592
A13: 12 | B13: =VLOOKUP(A13,PlantMaterial!B:C,2,0) -> AVISO | C13: N+ | D13: 1 | E13: 04545 | F13: 1 | G13: 2 | H13: 21 | M13: 2.73 | N13: 42586 | S13: 7.86 | T13: 42592 | U13: 13.5 | V13: 42586 | Y13: 3.86386 | Z13: 42592 | AA13: 45 | AB13: 42249 | AE13: 20.02 | AF13: 42586 | AI13: 140 | AJ13: 42507 | AK13: 9.9 | BG13: -8.4 | BH13: 42592 | BM13: 58.8 | BN13: 42592 | BQ13: 12.5 | BR13: 42592 | BS13: 43.076923 | BT13: 42592 | BU13: 21.208791 | BV13: 42592 | BW13: 17.362637 | BX13: 42592 | CA13: 37.2 | CB13: 42592
A14: 13 | B14: =VLOOKUP(A14,PlantMaterial!B:C,2,0) -> AM109 | C14: N+ | D14: 1 | E14: 04546 | F14: 1 | G14: 3 | H14: 31.5 | M14: 3.7 | N14: 42586 | S14: 11.54 | T14: 42592 | U14: 13.5 | V14: 42586 | Y14: 4.6172 | Z14: 42592 | AA14: 45 | AB14: 42249 | AE14: 27.16 | AF14: 42586 | AI14: 140 | AJ14: 42507 | AK14: 9.8 | BG14: -8.3 | BH14: 42592 | BM14: 59.2 | BN14: 42592 | BQ14: 11.6 | BR14: 42592 | BS14: 46.703297 | BT14: 42592 | BU14: 18.681319 | BV14: 42592 | BW14: 12.307692 | BX14: 42592 | CA14: 35.1 | CB14: 42592
A15: 14 | B15: =VLOOKUP(A15,PlantMaterial!B:C,2,0) -> MONTEGO | C15: N+ | D15: 1 | E15: 04547 | F15: 2 | G15: 3 | H15: 31.5 | I15: 18 | J15: 42430 | M15: 2.75 | N15: 42586 | S15: 8.24 | T15: 42592 | U15: 13.5 | V15: 42586 | Y15: 3.89474 | Z15: 42592 | AA15: 45 | AB15: 42249 | AE15: 20.18 | AF15: 42586 | AI15: 130 | AJ15: 42507 | AK15: 9.8 | BG15: -9.2 | BH15: 42592 | BM15: 60.9 | BN15: 42592 | BQ15: 11.2 | BR15: 42592 | BS15: 44.835165 | BT15: 42592 | BU15: 21.208791 | BV15: 42592 | BW15: 17.692308 | BX15: 42592 | CA15: 38.5 | CB15: 42592
A16: 15 | B16: =VLOOKUP(A16,PlantMaterial!B:C,2,0) -> DK038 | C16: N+ | D16: 1 | E16: 04548 | F16: 3 | G16: 3 | H16: 31.5 | M16: 2.84 | N16: 42586 | S16: 9.09 | T16: 42592 | U16: 13.5 | V16: 42586 | Y16: 3.46005 | Z16: 42592 | AA16: 45 | AB16: 42249 | AE16: 20.97 | AF16: 42586 | AI16: 140 | AJ16: 42507 | AK16: 9.3 | BG16: -8.1 | BH16: 42592 | BM16: 61.9 | BN16: 42592 | BQ16: 10.3 | BR16: 42592 | BS16: 47.692308 | BT16: 42592 | BU16: 18.131868 | BV16: 42592 | BW16: 12.307692 | BX16: 42592 | CA16: 34.6 | CB16: 42592
A17: 16 | B17: =VLOOKUP(A17,PlantMaterial!B:C,2,0) -> TENOR | C17: N+ | D17: 1 | E17: 04549 | F17: 4 | G17: 3 | H17: 31.5 | I17: 9 | J17: 42430 | M17: 2.49 | N17: 42586 | S17: 7.9 | T17: 42592 | U17: 13.5 | V17: 42586 | Y17: 3.2165 | Z17: 42592 | AA17: 45 | AB17: 42249 | AE17: 18.38 | AF17: 42586 | AI17: 145 | AJ17: 42507 | AK17: 9.3 | BG17: -7.4 | BH17: 42592 | BM17: 58.9 | BN17: 42592 | BQ17: 11.7 | BR17: 42592 | BS17: 47.252747 | BT17: 42592 | BU17: 19.230769 | BV17: 42592 | BW17: 17.472527 | BX17: 42592 | CA17: 36.5 | CB17: 42592
A18: 17 | B18: =VLOOKUP(A18,PlantMaterial!B:C,2,0) -> EXL4816 | C18: N+ | D18: 1 | E18: 04550 | F18: 5 | G18: 3 | H18: 31.5 | M18: 3.81 | N18: 42586 | S18: 11.44 | T18: 42592 | U18: 13.5 | V18: 42586 | Y18: 5.0508 | Z18: 42592 | AA18: 45 | AB18: 42249 | AE18: 28.06 | AF18: 42586 | AI18: 145 | AJ18: 42507 | AK18: 9.5 | BG18: -8.8 | BH18: 42592 | BM18: 59.3 | BN18: 42592 | BQ18: 11.8 | BR18: 42592 | BS18: 44.835165 | BT18: 42592 | BU18: 19.78022 | BV18: 42592 | BW18: 17.142857 | BX18: 42592 | CA18: 35.9 | CB18: 42592
A19: 18 | B19: =VLOOKUP(A19,PlantMaterial!B:C,2,0) -> EXPRESS | C19: N+ | D19: 1 | E19: 04551 | F19: 6 | G19: 3 | H19: 31.5 | M19: 2.53 | N19: 42586 | S19: 7.37 | T19: 42592 | U19: 13.5 | V19: 42586 | Y19: 3.6153 | Z19: 42592 | AA19: 45 | AB19: 42249 | AE19: 18.54 | AF19: 42586 | AI19: 140 | AJ19: 42507 | AK19: 10 | BG19: -8.4 | BH19: 42592 | BM19: 61.2 | BN19: 42592 | BQ19: 11 | BR19: 42592 | BS19: 43.736264 | BT19: 42592 | BU19: 21.428571 | BV19: 42592 | BW19: 20.43956 | BX19: 42592 | CA19: 38 | CB19: 42592
A20: 19 | B20: =VLOOKUP(A20,PlantMaterial!B:C,2,0) -> EXL3155 | C20: N+ | D20: 1 | E20: 04552 | F20: 6 | G20: 4 | H20: 42 | M20: 2.76 | N20: 42586 | S20: 8.29 | T20: 42592 | U20: 13.5 | V20: 42586 | Y20: 3.78862 | Z20: 42592 | AA20: 45 | AB20: 42249 | AE20: 20.26 | AF20: 42586 | AI20: 135 | AJ20: 42507 | AK20: 9.8 | BG20: -8.2 | BH20: 42592 | BM20: 59.3 | BN20: 42592 | BQ20: 11.3 | BR20: 42592 | BS20: 44.945055 | BT20: 42592 | BU20: 20.549451 | BV20: 42592 | BW20: 18.901099 | BX20: 42592 | CA20: 37.4 | CB20: 42592
A21: 20 | B21: =VLOOKUP(A21,PlantMaterial!B:C,2,0) -> C03-1ESQ0 | C21: N+ | D21: 1 | E21: 04553 | F21: 5 | G21: 4 | H21: 42 | M21: 3.91 | N21: 42586 | S21: 12.14 | T21: 42592 | U21: 13.5 | V21: 42586 | Y21: 4.91967 | Z21: 42592 | AA21: 45 | AB21: 42249 | AE21: 28.77 | AF21: 42586 | AI21: 140 | AJ21: 42507 | AK21: 9.6 | BG21: -8.9 | BH21: 42592 | BM21: 61.1 | BN21: 42592 | BQ21: 11.2 | BR21: 42592 | BS21: 46.373626 | BT21: 42592 | BU21: 18.791209 | BV21: 42592 | BW21: 14.285714 | BX21: 42592 | CA21: 35.1 | CB21: 42592
A22: 21 | B22: =VLOOKUP(A22,PlantMaterial!B:C,2,0) -> C03-1ESQ1 | C22: N+ | D22: 1 | E22: 04554 | F22: 4 | G22: 4 | H22: 42 | M22: 3.73 | N22: 42586 | S22: 11.54 | T22: 42592 | U22: 13.5 | V22: 42586 | Y22: 4.85157 | Z22: 42592 | AA22: 45 | AB22: 42249 | AE22: 27.41 | AF22: 42586 | AI22: 140 | AJ22: 42507 | AK22: 9.7 | BG22: -7.7 | BH22: 42592 | BM22: 59.6 | BN22: 42592 | BQ22: 11.7 | BR22: 42592 | BS22: 46.263736 | BT22: 42592 | BU22: 19.450549 | BV22: 42592 | BW22: 14.285714 | BX22: 42592 | CA22: 36.2 | CB22: 42592
A23: 22 | B23: =VLOOKUP(A23,PlantMaterial!B:C,2,0) -> C04-1ESQ0 | C23: N+ | D23: 1 | E23: 04555 | F23: 3 | G23: 4 | H23: 42 | M23: 3.33 | N23: 42586 | S23: 10.45 | T23: 42592 | U23: 13.5 | V23: 42586 | Y23: 4.14557 | Z23: 42592 | AA23: 45 | AB23: 42249 | AE23: 24.53 | AF23: 42586 | AI23: 140 | AJ23: 42507 | AK23: 9.5 | BG23: -8.8 | BH23: 42592 | BM23: 60.2 | BN23: 42592 | BQ23: 10.6 | BR23: 42592 | BS23: 46.813187 | BT23: 42592 | BU23: 18.571429 | BV23: 42592 | BW23: 13.626374 | BX23: 42592 | CA23: 34.9 | CB23: 42592
A24: 23 | B24: =VLOOKUP(A24,PlantMaterial!B:C,2,0) -> AVISO | C24: N+ | D24: 1 | E24: 04556 | F24: 2 | G24: 4 | H24: 42 | M24: 3 | N24: 42586 | S24: 8.88 | T24: 42592 | U24: 13.5 | V24: 42586 | Y24: 4.0737 | Z24: 42592 | AA24: 45 | AB24: 42249 | AE24: 22.02 | AF24: 42586 | AI24: 140 | AJ24: 42507 | AK24: 9.8 | BG24: -8.9 | BH24: 42592 | BM24: 59.5 | BN24: 42592 | BQ24: 11.6 | BR24: 42592 | BS24: 44.285714 | BT24: 42592 | BU24: 20.32967 | BV24: 42592 | BW24: 15.604396 | BX24: 42592 | CA24: 36.6 | CB24: 42592
A25: 24 | B25: =VLOOKUP(A25,PlantMaterial!B:C,2,0) -> C04-1ESQ1 | C25: N+ | D25: 1 | E25: 04557 | F25: 1 | G25: 4 | H25: 42 | M25: 2.47 | N25: 42586 | S25: 7.58 | T25: 42592 | U25: 13.5 | V25: 42586 | Y25: 3.178 | Z25: 42592 | AA25: 45 | AB25: 42249 | AE25: 18.16 | AF25: 42586 | AI25: 140 | AJ25: 42507 | AK25: 9.7 | BG25: -9.3 | BH25: 42592 | BM25: 59.3 | BN25: 42592 | BQ25: 11 | BR25: 42592 | BS25: 45.824176 | BT25: 42592 | BU25: 19.230769 | BV25: 42592 | BW25: 13.296703 | BX25: 42592 | CA25: 35.6 | CB25: 42592
A26: 25 | B26: =VLOOKUP(A26,PlantMaterial!B:C,2,0) -> MONTEGO | C26: N+ | D26: 1 | E26: 04558 | F26: 1 | G26: 5 | H26: 52.5 | M26: 2.54 | N26: 42586 | S26: 7.76 | T26: 42592 | U26: 13.5 | V26: 42586 | Y26: 3.50432 | Z26: 42592 | AA26: 45 | AB26: 42249 | AE26: 18.64 | AF26: 42586 | AI26: 120 | AJ26: 42507 | AK26: 9.8 | BG26: -10 | BH26: 42592 | BM26: 59.5 | BN26: 42592 | BQ26: 11.4 | BR26: 42592 | BS26: 45.714286 | BT26: 42592 | BU26: 20.659341 | BV26: 42592 | BW26: 15.274725 | BX26: 42592 | CA26: 38 | CB26: 42592
A27: 26 | B27: =VLOOKUP(A27,PlantMaterial!B:C,2,0) -> RAPSO_304 | C27: N+ | D27: 1 | E27: 04559 | F27: 2 | G27: 5 | H27: 52.5 | M27: 3.21 | N27: 42586 | S27: 9.82 | T27: 42592 | U27: 13.5 | V27: 42586 | Y27: 4.2462 | Z27: 42592 | AA27: 45 | AB27: 42249 | AE27: 23.59 | AF27: 42586 | AI27: 135 | AJ27: 42507 | AK27: 9.7 | BG27: -11.1 | BH27: 42592 | BM27: 60.1 | BN27: 42592 | BQ27: 12 | BR27: 42592 | BS27: 45.714286 | BT27: 42592 | BU27: 19.78022 | BV27: 42592 | BW27: 14.835165 | BX27: 42592 | CA27: 36.5 | CB27: 42592
A28: 27 | B28: =VLOOKUP(A28,PlantMaterial!B:C,2,0) -> TENOR | C28: N+ | D28: 1 | E28: 04560 | F28: 3 | G28: 5 | H28: 52.5 | M28: 2.56 | N28: 42586 | S28: 7.93 | T28: 42592 | U28: 13.5 | V28: 42586 | Y28: 3.304 | Z28: 42592 | AA28: 45 | AB28: 42249 | AE28: 18.88 | AF28: 42586 | AI28: 135 | AJ28: 42507 | AK28: 9.4 | BG28: -7.7 | BH28: 42592 | BM28: 59.2 | BN28: 42592 | BQ28: 11.4 | BR28: 42592 | BS28: 46.153846 | BT28: 42592 | BU28: 19.230769 | BV28: 42592 | BW28: 17.362637 | BX28: 42592 | CA28: 35.6 | CB28: 42592
A29: 28 | B29: =VLOOKUP(A29,PlantMaterial!B:C,2,0) -> LEL17 | C29: N+ | D29: 1 | E29: 04561 | F29: 4 | G29: 5 | H29: 52.5 | M29: 4.7 | N29: 42586 | S29: 14.45 | T29: 42592 | U29: 13.5 | V29: 42586 | Y29: 5.9166 | Z29: 42592 | AA29: 45 | AB29: 42249 | AE29: 34.6 | AF29: 42586 | AI29: 135 | AJ29: 42507 | AK29: 9.6 | BG29: -9.1 | BH29: 42592 | BM29: 61.6 | BN29: 42592 | BQ29: 10.7 | BR29: 42592 | BS29: 45.934066 | BT29: 42592 | BU29: 18.791209 | BV29: 42592 | BW29: 14.285714 | BX29: 42592 | CA29: 34.7 | CB29: 42592
A30: 29 | B30: =VLOOKUP(A30,PlantMaterial!B:C,2,0) -> EXPRESS | C30: N+ | D30: 1 | E30: 04562 | F30: 5 | G30: 5 | H30: 52.5 | I30: 27 | J30: 42430 | M30: 2.12 | N30: 42586 | S30: 6.34 | T30: 42592 | U30: 13.5 | V30: 42586 | Y30: 2.91533 | Z30: 42592 | AA30: 45 | AB30: 42249 | AE30: 15.59 | AF30: 42586 | AI30: 125 | AJ30: 42507 | AK30: 9.7 | BG30: -9.1 | BH30: 42592 | BM30: 61.1 | BN30: 42592 | BQ30: 10.7 | BR30: 42592 | BS30: 44.725275 | BT30: 42592 | BU30: 20.549451 | BV30: 42592 | BW30: 17.802198 | BX30: 42592 | CA30: 37 | CB30: 42592
A31: 30 | B31: =VLOOKUP(A31,PlantMaterial!B:C,2,0) -> C04-1LEQ0 | C31: N+ | D31: 1 | E31: 04563 | F31: 6 | G31: 5 | H31: 52.5 | M31: 3.07 | N31: 42586 | S31: 9.52 | T31: 42592 | U31: 13.5 | V31: 42586 | Y31: 4.068 | Z31: 42592 | AA31: 45 | AB31: 42249 | AE31: 22.6 | AF31: 42586 | AI31: 135 | AJ31: 42507 | AK31: 9.6 | BG31: -10.3 | BH31: 42592 | BM31: 60.5 | BN31: 42592 | BQ31: 11 | BR31: 42592 | BS31: 46.263736 | BT31: 42592 | BU31: 19.78022 | BV31: 42592 | BW31: 16.703297 | BX31: 42592 | CA31: 36.8 | CB31: 42592
A32: 31 | B32: =VLOOKUP(A32,PlantMaterial!B:C,2,0) -> C04-1LEQ1 | C32: N+ | D32: 1 | E32: 04564 | F32: 6 | G32: 6 | H32: 63 | M32: 3.18 | N32: 42586 | S32: 9.88 | T32: 42592 | U32: 13.5 | V32: 42586 | Y32: 4.02652 | Z32: 42592 | AA32: 45 | AB32: 42249 | AE32: 23.41 | AF32: 42586 | AI32: 150 | AJ32: 42507 | AK32: 9.6 | BG32: -11 | BH32: 42592 | BM32: 61.5 | BN32: 42592 | BQ32: 10.1 | BR32: 42592 | BS32: 46.373626 | BT32: 42592 | BU32: 18.901099 | BV32: 42592 | BW32: 16.043956 | BX32: 42592 | CA32: 35.2 | CB32: 42592
A33: 32 | B33: =VLOOKUP(A33,PlantMaterial!B:C,2,0) -> A05-1LEQ0 | C33: N+ | D33: 1 | E33: 04565 | F33: 5 | G33: 6 | H33: 63 | M33: 3.37 | N33: 42586 | S33: 10.02 | T33: 42592 | U33: 13.5 | V33: 42586 | Y33: 4.51542 | Z33: 42592 | AA33: 45 | AB33: 42249 | AE33: 24.81 | AF33: 42586 | AI33: 150 | AJ33: 42507 | AK33: 9.5 | BG33: -7.8 | BH33: 42592 | BM33: 61 | BN33: 42592 | BQ33: 10.3 | BR33: 42592 | BS33: 44.395604 | BT33: 42592 | BU33: 20 | BV33: 42592 | BW33: 18.571429 | BX33: 42592 | CA33: 35.9 | CB33: 42592
A34: 33 | B34: =VLOOKUP(A34,PlantMaterial!B:C,2,0) -> A05-1LEQ1 | C34: N+ | D34: 1 | E34: 04566 | F34: 4 | G34: 6 | H34: 63 | M34: 4.26 | N34: 42586 | S34: 12.83 | T34: 42592 | U34: 13.5 | V34: 42586 | Y34: 5.67797 | Z34: 42592 | AA34: 45 | AB34: 42249 | AE34: 31.37 | AF34: 42586 | AI34: 150 | AJ34: 42507 | AK34: 9.5 | BG34: -8.2 | BH34: 42592 | BM34: 62.8 | BN34: 42592 | BQ34: 10 | BR34: 42592 | BS34: 44.945055 | BT34: 42592 | BU34: 19.89011 | BV34: 42592 | BW34: 19.67033 | BX34: 42592 | CA34: 36.1 | CB34: 42592
A35: 34 | B35: =VLOOKUP(A35,PlantMaterial!B:C,2,0) -> RAPSO_4 | C35: N+ | D35: 1 | E35: 04567 | F35: 3 | G35: 6 | H35: 63 | M35: 3.17 | N35: 42586 | S35: 10.07 | T35: 42592 | U35: 13.5 | V35: 42586 | Y35: 4.02136 | Z35: 42592 | AA35: 45 | AB35: 42249 | AE35: 23.38 | AF35: 42586 | AI35: 130 | AJ35: 42507 | AK35: 9.4 | BG35: -7.8 | BH35: 42592 | BM35: 62.4 | BN35: 42592 | BQ35: 10.4 | BR35: 42592 | BS35: 47.362637 | BT35: 42592 | BU35: 18.901099 | BV35: 42592 | BW35: 13.956044 | BX35: 42592 | CA35: 36 | CB35: 42592
A36: 35 | B36: =VLOOKUP(A36,PlantMaterial!B:C,2,0) -> C04-1MASQ0 | C36: N+ | D36: 1 | E36: 04568 | F36: 2 | G36: 6 | H36: 63 | M36: 3.16 | N36: 42586 | S36: 9.9 | T36: 42592 | U36: 13.5 | V36: 42586 | Y36: 4.02917 | Z36: 42592 | AA36: 45 | AB36: 42249 | AE36: 23.29 | AF36: 42586 | AI36: 140 | AJ36: 42507 | AK36: 9.5 | BG36: -8.8 | BH36: 42592 | BM36: 63.5 | BN36: 42592 | BQ36: 10.1 | BR36: 42592 | BS36: 46.703297 | BT36: 42592 | BU36: 19.010989 | BV36: 42592 | BW36: 15.274725 | BX36: 42592 | CA36: 35.7 | CB36: 42592
A37: 36 | B37: =VLOOKUP(A37,PlantMaterial!B:C,2,0) -> C04-1MASQ1 | C37: N+ | D37: 1 | E37: 04569 | F37: 1 | G37: 6 | H37: 63 | M37: 2.93 | N37: 42586 | S37: 8.91 | T37: 42592 | U37: 13.5 | V37: 42586 | Y37: 3.98305 | Z37: 42592 | AA37: 45 | AB37: 42249 | AE37: 21.53 | AF37: 42586 | AI37: 140 | AJ37: 42507 | AK37: 9.7 | BG37: -8.6 | BH37: 42592 | BM37: 61.2 | BN37: 42592 | BQ37: 10.7 | BR37: 42592 | BS37: 45.494505 | BT37: 42592 | BU37: 20.32967 | BV37: 42592 | BW37: 15.164835 | BX37: 42592 | CA37: 37.3 | CB37: 42592
A38: 37 | B38: =VLOOKUP(A38,PlantMaterial!B:C,2,0) -> RAPSO_323 | C38: N+ | D38: 1 | E38: 04570 | F38: 1 | G38: 7 | H38: 73.5 | M38: 3.53 | N38: 42586 | S38: 10.81 | T38: 42592 | U38: 13.5 | V38: 42586 | Y38: 4.4289 | Z38: 42592 | AA38: 45 | AB38: 42249 | AE38: 25.9 | AF38: 42586 | AI38: 160 | AJ38: 42507 | AK38: 9.9 | BG38: -10.2 | BH38: 42592 | BM38: 61.9 | BN38: 42592 | BQ38: 10.4 | BR38: 42592 | BS38: 45.934066 | BT38: 42592 | BU38: 18.791209 | BV38: 42592 | BW38: 13.846154 | BX38: 42592 | CA38: 34.6 | CB38: 42592
A39: 38 | B39: =VLOOKUP(A39,PlantMaterial!B:C,2,0) -> C04-1RAGTQ0 | C39: N+ | D39: 1 | E39: 04571 | F39: 2 | G39: 7 | H39: 73.5 | M39: 3.31 | N39: 42586 | S39: 10.42 | T39: 42592 | U39: 13.5 | V39: 42586 | Y39: 4.04044 | Z39: 42592 | AA39: 45 | AB39: 42249 | AE39: 24.34 | AF39: 42586 | AI39: 155 | AJ39: 42507 | AK39: 9.7 | BG39: -8.3 | BH39: 42592 | BM39: 62.3 | BN39: 42592 | BQ39: 10 | BR39: 42592 | BS39: 47.032967 | BT39: 42592 | BU39: 18.241758 | BV39: 42592 | BW39: 11.868132 | BX39: 42592 | CA39: 34.4 | CB39: 42592
A40: 39 | B40: =VLOOKUP(A40,PlantMaterial!B:C,2,0) -> C04-1RAGTQ1 | C40: N+ | D40: 1 | E40: 04572 | F40: 3 | G40: 7 | H40: 73.5 | M40: 2.95 | N40: 42586 | S40: 9.25 | T40: 42592 | U40: 13.5 | V40: 42586 | Y40: 3.66899 | Z40: 42592 | AA40: 45 | AB40: 42249 | AE40: 21.71 | AF40: 42586 | AI40: 155 | AJ40: 42507 | AK40: 9.6 | BG40: -8.5 | BH40: 42592 | BM40: 61.3 | BN40: 42592 | BQ40: 10.5 | BR40: 42592 | BS40: 46.813187 | BT40: 42592 | BU40: 18.571429 | BV40: 42592 | BW40: 11.978022 | BX40: 42592 | CA40: 35 | CB40: 42592
A41: 40 | B41: =VLOOKUP(A41,PlantMaterial!B:C,2,0) -> RAPSO_325 | C41: N+ | D41: 1 | E41: 04573 | F41: 4 | G41: 7 | H41: 73.5 | M41: 4.72 | N41: 42586 | S41: 14.75 | T41: 42592 | U41: 13.5 | V41: 42586 | Y41: 5.7321 | Z41: 42592 | AA41: 45 | AB41: 42249 | AE41: 34.74 | AF41: 42586 | AI41: 155 | AJ41: 42507 | AK41: 9.6 | BG41: -7.2 | BH41: 42592 | BM41: 63.3 | BN41: 42592 | BQ41: 9.9 | BR41: 42592 | BS41: 46.703297 | BT41: 42592 | BU41: 18.131868 | BV41: 42592 | BW41: 17.032967 | BX41: 42592 | CA41: 33.9 | CB41: 42592
A42: 41 | B42: =VLOOKUP(A42,PlantMaterial!B:C,2,0) -> C04-1SYNQ0 | C42: N+ | D42: 1 | E42: 04574 | F42: 5 | G42: 7 | H42: 73.5 | M42: 3.23 | N42: 42586 | S42: 10.1 | T42: 42592 | U42: 13.5 | V42: 42586 | Y42: 4.158 | Z42: 42592 | AA42: 45 | AB42: 42249 | AE42: 23.76 | AF42: 42586 | AI42: 140 | AJ42: 42507 | AK42: 9.6 | BG42: -8.7 | BH42: 42592 | BM42: 63.7 | BN42: 42592 | BQ42: 10.4 | BR42: 42592 | BS42: 46.703297 | BT42: 42592 | BU42: 19.230769 | BV42: 42592 | BW42: 14.285714 | BX42: 42592 | CA42: 36.1 | CB42: 42592
A43: 42 | B43: =VLOOKUP(A43,PlantMaterial!B:C,2,0) -> C04-1SYNQ1 | C43: N+ | D43: 1 | E43: 04575 | F43: 6 | G43: 7 | H43: 73.5 | M43: 3.29 | N43: 42586 | S43: 10.46 | T43: 42592 | U43: 13.5 | V43: 42586 | Y43: 4.0572 | Z43: 42592 | AA43: 45 | AB43: 42249 | AE43: 24.15 | AF43: 42586 | AI43: 140 | AJ43: 42507 | AK43: 9.8 | BG43: -8.8 | BH43: 42592 | BM43: 64 | BN43: 42592 | BQ43: 10.3 | BR43: 42592 | BS43: 47.582418 | BT43: 42592 | BU43: 18.461538 | BV43: 42592 | BW43: 14.945055 | BX43: 42592 | CA43: 35.2 | CB43: 42592
A44: 1 | B44: =VLOOKUP(A44,PlantMaterial!B:C,2,0) -> AVISO | C44: N+ | D44: 2 | E44: used for INN | F44: 1 | G44: 14 | H44: 147 | I44: 16 | J44: 42430 | M44: 2.47 | N44: 42586 | S44: 7.44 | T44: 42592 | U44: 13.5 | V44: 42586 | Y44: 3.33592 | Z44: 42592 | AA44: 45 | AB44: 42249 | AE44: 18.13 | AF44: 42586 | AI44: 145 | AJ44: 42507 | AK44: 9.8 | BG44: -10.1 | BH44: 42592 | BM44: 58.6 | BN44: 42592 | BQ44: 12.1 | BR44: 42592 | BS44: 45.054945 | BT44: 42592 | BU44: 20.21978 | BV44: 42592 | BW44: 17.362637 | BX44: 42592 | CA44: 36.9 | CB44: 42592
A45: 2 | B45: =VLOOKUP(A45,PlantMaterial!B:C,2,0) -> A05-AMQ0 | C45: N+ | D45: 2 | E45: 04587 | F45: 6 | G45: 9 | H45: 94.5 | M45: 2.62 | N45: 42586 | S45: 8.18 | T45: 42592 | U45: 13.5 | V45: 42586 | Y45: 3.4265 | Z45: 42592 | AA45: 45 | AB45: 42249 | AE45: 19.25 | AF45: 42586 | AI45: 135 | AJ45: 42507 | AK45: 9.8 | BG45: -9.1 | BH45: 42592 | BM45: 61.6 | BN45: 42592 | BQ45: 11 | BR45: 42592 | BS45: 46.703297 | BT45: 42592 | BU45: 19.56044 | BV45: 42592 | BW45: 14.065934 | BX45: 42592 | CA45: 36.8 | CB45: 42592
A46: 3 | B46: =VLOOKUP(A46,PlantMaterial!B:C,2,0) -> MONTEGO | C46: N+ | D46: 2 | E46: used for INN | F46: 2 | G46: 13 | H46: 136.5 | M46: 2.96 | N46: 42586 | S46: 9.08 | T46: 42592 | U46: 13.5 | V46: 42586 | Y46: 4.08524 | Z46: 42592 | AA46: 45 | AB46: 42249 | AE46: 21.73 | AF46: 42586 | AI46: 135 | AJ46: 42507 | AK46: 9.8 | BG46: -8.7 | BH46: 42592 | BM46: 61.1 | BN46: 42592 | BQ46: 11.1 | BR46: 42592 | BS46: 45.934066 | BT46: 42592 | BU46: 20.659341 | BV46: 42592 | BW46: 16.593407 | BX46: 42592 | CA46: 38.2 | CB46: 42592
A47: 4 | B47: =VLOOKUP(A47,PlantMaterial!B:C,2,0) -> A05-AMQ1 | C47: N+ | D47: 2 | E47: 04610 | F47: 5 | G47: 13 | H47: 136.5 | M47: 2.66 | N47: 42586 | S47: 8.13 | T47: 42592 | U47: 13.5 | V47: 42586 | Y47: 3.60088 | Z47: 42592 | AA47: 45 | AB47: 42249 | AE47: 19.57 | AF47: 42586 | AI47: 135 | AJ47: 42507 | AK47: 9.6 | BG47: -8.9 | BH47: 42592 | BM47: 60.9 | BN47: 42592 | BQ47: 11.1 | BR47: 42592 | BS47: 45.714286 | BT47: 42592 | BU47: 20.21978 | BV47: 42592 | BW47: 18.571429 | BX47: 42592 | CA47: 37.3 | CB47: 42592
A48: 5 | B48: =VLOOKUP(A48,PlantMaterial!B:C,2,0) -> TENOR | C48: N+ | D48: 2 | E48: used for INN | F48: 1 | G48: 13 | H48: 136.5 | M48: 2.69 | N48: 42586 | S48: 8.26 | T48: 42592 | U48: 13.5 | V48: 42586 | Y48: 3.57837 | Z48: 42592 | AA48: 45 | AB48: 42249 | AE48: 19.77 | AF48: 42586 | AI48: 135 | AJ48: 42507 | AK48: 9.7 | BG48: -7.4 | BH48: 42592 | BM48: 60.4 | BN48: 42592 | BQ48: 11.5 | BR48: 42592 | BS48: 45.934066 | BT48: 42592 | BU48: 19.89011 | BV48: 42592 | BW48: 16.813187 | BX48: 42592 | CA48: 36.8 | CB48: 42592
A49: 6 | B49: =VLOOKUP(A49,PlantMaterial!B:C,2,0) -> C03-AMQ0 | C49: N+ | D49: 2 | E49: 04609 | F49: 4 | G49: 13 | H49: 136.5 | M49: 2.98 | N49: 42586 | S49: 9.17 | T49: 42592 | U49: 13.5 | V49: 42586 | Y49: 4.01319 | Z49: 42592 | AA49: 45 | AB49: 42249 | AE49: 21.93 | AF49: 42586 | AI49: 135 | AJ49: 42507 | AK49: 9.6 | BG49: -7.5 | BH49: 42592 | BM49: 60.2 | BN49: 42592 | BQ49: 11.6 | BR49: 42592 | BS49: 45.934066 | BT49: 42592 | BU49: 20.10989 | BV49: 42592 | BW49: 15.274725 | BX49: 42592 | CA49: 37.2 | CB49: 42592
A50: 7 | B50: =VLOOKUP(A50,PlantMaterial!B:C,2,0) -> EXPRESS | C50: N+ | D50: 2 | E50: used for INN | F50: 4 | G50: 11 | H50: 115.5 | M50: 2.37 | N50: 42586 | S50: 7.41 | T50: 42592 | U50: 13.5 | V50: 42586 | Y50: 3.0485 | Z50: 42592 | AA50: 45 | AB50: 42249 | AE50: 17.42 | AF50: 42586 | AI50: 140 | AJ50: 42507 | AK50: 9.7 | BG50: -8.2 | BH50: 42592 | BM50: 61.6 | BN50: 42592 | BQ50: 10.5 | BR50: 42592 | BS50: 46.813187 | BT50: 42592 | BU50: 19.230769 | BV50: 42592 | BW50: 20.10989 | BX50: 42592 | CA50: 36.2 | CB50: 42592
A51: 8 | B51: =VLOOKUP(A51,PlantMaterial!B:C,2,0) -> C03-AMQ1 | C51: N+ | D51: 2 | E51: 04602 | F51: 3 | G51: 12 | H51: 126 | M51: 2.73 | N51: 42586 | S51: 8.53 | T51: 42592 | U51: 13.5 | V51: 42586 | Y51: 3.618 | Z51: 42592 | AA51: 45 | AB51: 42249 | AE51: 20.1 | AF51: 42586 | AI51: 140 | AJ51: 42507 | AK51: 9.5 | BG51: -6.1 | BH51: 42592 | BM51: 61.3 | BN51: 42592 | BQ51: 11.1 | BR51: 42592 | BS51: 46.593407 | BT51: 42592 | BU51: 19.78022 | BV51: 42592 | BW51: 13.846154 | BX51: 42592 | CA51: 37.1 | CB51: 42592
A52: 9 | B52: =VLOOKUP(A52,PlantMaterial!B:C,2,0) -> C04-DKQ0 | C52: N+ | D52: 2 | E52: 04594 | F52: 1 | G52: 11 | H52: 115.5 | M52: 2.24 | N52: 42586 | S52: 6.82 | T52: 42592 | U52: 13.5 | V52: 42586 | Y52: 2.98107 | Z52: 42592 | AA52: 45 | AB52: 42249 | AE52: 16.47 | AF52: 42586 | AI52: 140 | AJ52: 42507 | AK52: 9.7 | BG52: -6.9 | BH52: 42592 | BM52: 58.6 | BN52: 42592 | BQ52: 11.6 | BR52: 42592 | BS52: 45.494505 | BT52: 42592 | BU52: 19.89011 | BV52: 42592 | BW52: 16.373626 | BX52: 42592 | CA52: 36.4 | CB52: 42592
A53: 10 | B53: =VLOOKUP(A53,PlantMaterial!B:C,2,0) -> C04-DKQ1 | C53: N+ | D53: 2 | E53: 04601 | F53: 2 | G53: 12 | H53: 126 | M53: 2.75 | N53: 42586 | S53: 8.55 | T53: 42592 | U53: 13.5 | V53: 42586 | Y53: 3.726 | Z53: 42592 | AA53: 45 | AB53: 42249 | AE53: 20.25 | AF53: 42586 | AI53: 140 | AJ53: 42507 | AK53: 9.6 | BG53: -6.9 | BH53: 42592 | BM53: 60.6 | BN53: 42592 | BQ53: 11 | BR53: 42592 | BS53: 46.373626 | BT53: 42592 | BU53: 20.21978 | BV53: 42592 | BW53: 16.043956 | BX53: 42592 | CA53: 37.7 | CB53: 42592
A54: 11 | B54: =VLOOKUP(A54,PlantMaterial!B:C,2,0) -> AM087 | C54: N+ | D54: 2 | E54: 04611 | F54: 6 | G54: 13 | H54: 136.5 | M54: 3.41 | N54: 42586 | S54: 10.74 | T54: 42592 | U54: 13.5 | V54: 42586 | Y54: 4.35696 | Z54: 42592 | AA54: 45 | AB54: 42249 | AE54: 25.04 | AF54: 42586 | AI54: 135 | AJ54: 42507 | AK54: 9.8 | BG54: -6.6 | BH54: 42592 | BM54: 62.8 | BN54: 42592 | BQ54: 10.7 | BR54: 42592 | BS54: 47.142857 | BT54: 42592 | BU54: 19.120879 | BV54: 42592 | BW54: 17.582418 | BX54: 42592 | CA54: 36.2 | CB54: 42592
A55: 12 | B55: =VLOOKUP(A55,PlantMaterial!B:C,2,0) -> AVISO | C55: N+ | D55: 2 | E55: 04614 | F55: 3 | G55: 14 | H55: 147 | M55: 2.85 | N55: 42586 | S55: 8.84 | T55: 42592 | U55: 13.5 | V55: 42586 | Y55: 3.69072 | Z55: 42592 | AA55: 45 | AB55: 42249 | AE55: 20.97 | AF55: 42586 | AI55: 145 | AJ55: 42507 | AK55: 9.6 | BG55: -8.3 | BH55: 42592 | BM55: 60.3 | BN55: 42592 | BQ55: 11.4 | BR55: 42592 | BS55: 46.373626 | BT55: 42592 | BU55: 19.340659 | BV55: 42592 | BW55: 15.604396 | BX55: 42592 | CA55: 36 | CB55: 42592
A56: 13 | B56: =VLOOKUP(A56,PlantMaterial!B:C,2,0) -> AM109 | C56: N+ | D56: 2 | E56: 04577 | F56: 2 | G56: 8 | H56: 84 | M56: 3.71 | N56: 42586 | S56: 11.57 | T56: 42592 | U56: 13.5 | V56: 42586 | Y56: 4.88491 | Z56: 42592 | AA56: 45 | AB56: 42249 | AE56: 27.29 | AF56: 42586 | AI56: 130 | AJ56: 42507 | AK56: 9.6 | BG56: -8.2 | BH56: 42592 | BM56: 59.2 | BN56: 42592 | BQ56: 11.9 | BR56: 42592 | BS56: 46.593407 | BT56: 42592 | BU56: 19.67033 | BV56: 42592 | BW56: 11.758242 | BX56: 42592 | CA56: 36.8 | CB56: 42592
A57: 14 | B57: =VLOOKUP(A57,PlantMaterial!B:C,2,0) -> MONTEGO | C57: N+ | D57: 2 | E57: 04586 | F57: 5 | G57: 9 | H57: 94.5 | I57: 27 | J57: 42430 | M57: 2.98 | N57: 42586 | S57: 9.08 | T57: 42592 | U57: 13.5 | V57: 42586 | Y57: 4.1266 | Z57: 42592 | AA57: 45 | AB57: 42249 | AE57: 21.95 | AF57: 42586 | AI57: 130 | AJ57: 42507 | AK57: 9.5 | BG57: -8.1 | BH57: 42592 | BM57: 60.4 | BN57: 42592 | BQ57: 11.3 | BR57: 42592 | BS57: 45.494505 | BT57: 42592 | BU57: 20.659341 | BV57: 42592 | BW57: 16.923077 | BX57: 42592 | CA57: 38 | CB57: 42592
A58: 15 | B58: =VLOOKUP(A58,PlantMaterial!B:C,2,0) -> DK038 | C58: N+ | D58: 2 | E58: 04598 | F58: 5 | G58: 11 | H58: 115.5 | M58: 2.37 | N58: 42586 | S58: 7.52 | T58: 42592 | U58: 13.5 | V58: 42586 | Y58: 3.04152 | Z58: 42592 | AA58: 45 | AB58: 42249 | AE58: 17.48 | AF58: 42586 | AI58: 140 | AJ58: 42507 | AK58: 9.4 | BG58: -7.7 | BH58: 42592 | BM58: 61.7 | BN58: 42592 | BQ58: 10.5 | BR58: 42592 | BS58: 47.252747 | BT58: 42592 | BU58: 19.120879 | BV58: 42592 | BW58: 15.494505 | BX58: 42592 | CA58: 36.2 | CB58: 42592
A59: 16 | B59: =VLOOKUP(A59,PlantMaterial!B:C,2,0) -> TENOR | C59: N+ | D59: 2 | E59: 04589 | F59: 2 | G59: 10 | H59: 105 | I59: 16 | J59: 42430 | M59: 2.59 | N59: 42586 | S59: 8.33 | T59: 42592 | U59: 13.5 | V59: 42586 | Y59: 3.30084 | Z59: 42592 | AA59: 45 | AB59: 42249 | AE59: 19.08 | AF59: 42586 | AI59: 150 | AJ59: 42507 | AK59: 9.5 | BG59: -6.3 | BH59: 42592 | BM59: 60 | BN59: 42592 | BQ59: 11.7 | BR59: 42592 | BS59: 48.021978 | BT59: 42592 | BU59: 19.010989 | BV59: 42592 | BW59: 18.241758 | BX59: 42592 | CA59: 36.5 | CB59: 42592
A60: 17 | B60: =VLOOKUP(A60,PlantMaterial!B:C,2,0) -> EXL4816 | C60: N+ | D60: 2 | E60: 04593 | F60: 6 | G60: 10 | H60: 105 | M60: 4.21 | N60: 42586 | S60: 13.13 | T60: 42592 | U60: 13.5 | V60: 42586 | Y60: 5.3234 | Z60: 42592 | AA60: 45 | AB60: 42249 | AE60: 30.95 | AF60: 42586 | AI60: 150 | AJ60: 42507 | AK60: 9.7 | BG60: -7.5 | BH60: 42592 | BM60: 60.1 | BN60: 42592 | BQ60: 11.4 | BR60: 42592 | BS60: 46.593407 | BT60: 42592 | BU60: 18.901099 | BV60: 42592 | BW60: 14.175824 | BX60: 42592 | CA60: 35.4 | CB60: 42592
A61: 18 | B61: =VLOOKUP(A61,PlantMaterial!B:C,2,0) -> EXPRESS | C61: N+ | D61: 2 | E61: 04613 | F61: 2 | G61: 14 | H61: 147 | M61: 2.4 | N61: 42586 | S61: 7.28 | T61: 42592 | U61: 13.5 | V61: 42586 | Y61: 3.36733 | Z61: 42592 | AA61: 45 | AB61: 42249 | AE61: 17.63 | AF61: 42586 | AI61: 145 | AJ61: 42507 | AK61: 9.8 | BG61: -7.2 | BH61: 42592 | BM61: 61.2 | BN61: 42592 | BQ61: 10.9 | BR61: 42592 | BS61: 45.384615 | BT61: 42592 | BU61: 20.989011 | BV61: 42592 | BW61: 18.571429 | BX61: 42592 | CA61: 38.5 | CB61: 42592
A62: 19 | B62: =VLOOKUP(A62,PlantMaterial!B:C,2,0) -> EXL3155 | C62: N+ | D62: 2 | E62: 04583 | F62: 2 | G62: 9 | H62: 94.5 | M62: 3.25 | N62: 42586 | S62: 10.21 | T62: 42592 | U62: 13.5 | V62: 42586 | Y62: 4.37919 | Z62: 42592 | AA62: 45 | AB62: 42249 | AE62: 23.93 | AF62: 42586 | AI62: 145 | AJ62: 42507 | AK62: 9.5 | BG62: -8.5 | BH62: 42592 | BM62: 59.8 | BN62: 42592 | BQ62: 12.1 | BR62: 42592 | BS62: 46.923077 | BT62: 42592 | BU62: 20.10989 | BV62: 42592 | BW62: 16.703297 | BX62: 42592 | CA62: 37.8 | CB62: 42592
A63: 20 | B63: =VLOOKUP(A63,PlantMaterial!B:C,2,0) -> C03-1ESQ0 | C63: N+ | D63: 2 | E63: 04617 | F63: 6 | G63: 14 | H63: 147 | M63: 3.8 | N63: 42586 | S63: 11.93 | T63: 42592 | U63: 13.5 | V63: 42586 | Y63: 4.86678 | Z63: 42592 | AA63: 45 | AB63: 42249 | AE63: 27.97 | AF63: 42586 | AI63: 145 | AJ63: 42507 | AK63: 9.6 | BG63: -8.6 | BH63: 42592 | BM63: 62.2 | BN63: 42592 | BQ63: 10.9 | BR63: 42592 | BS63: 46.923077 | BT63: 42592 | BU63: 19.120879 | BV63: 42592 | BW63: 14.835165 | BX63: 42592 | CA63: 35.9 | CB63: 42592
A64: 21 | B64: =VLOOKUP(A64,PlantMaterial!B:C,2,0) -> C03-1ESQ1 | C64: N+ | D64: 2 | E64: 04600 | F64: 1 | G64: 12 | H64: 126 | M64: 3.49 | N64: 42586 | S64: 10.51 | T64: 42592 | U64: 13.5 | V64: 42586 | Y64: 4.72144 | Z64: 42592 | AA64: 45 | AB64: 42249 | AE64: 25.66 | AF64: 42586 | AI64: 140 | AJ64: 42507 | AK64: 9.7 | BG64: -7 | BH64: 42592 | BM64: 59.8 | BN64: 42592 | BQ64: 11.7 | BR64: 42592 | BS64: 45.054945 | BT64: 42592 | BU64: 20.21978 | BV64: 42592 | BW64: 16.263736 | BX64: 42592 | CA64: 36.7 | CB64: 42592
A65: 22 | B65: =VLOOKUP(A65,PlantMaterial!B:C,2,0) -> C04-1ESQ0 | C65: N+ | D65: 2 | E65: 04603 | F65: 4 | G65: 12 | H65: 126 | M65: 2.99 | N65: 42586 | S65: 9.18 | T65: 42592 | U65: 13.5 | V65: 42586 | Y65: 3.9636 | Z65: 42592 | AA65: 45 | AB65: 42249 | AE65: 22.02 | AF65: 42586 | AI65: 140 | AJ65: 42507 | AK65: 9.5 | BG65: -5.9 | BH65: 42592 | BM65: 60.5 | BN65: 42592 | BQ65: 10.8 | BR65: 42592 | BS65: 45.824176 | BT65: 42592 | BU65: 19.78022 | BV65: 42592 | BW65: 16.923077 | BX65: 42592 | CA65: 36.4 | CB65: 42592
A66: 23 | B66: =VLOOKUP(A66,PlantMaterial!B:C,2,0) -> AVISO | C66: N+ | D66: 2 | E66: 04590 | F66: 3 | G66: 10 | H66: 105 | M66: 3.02 | N66: 42586 | S66: 9.16 | T66: 42592 | U66: 13.5 | V66: 42586 | Y66: 3.9996 | Z66: 42592 | AA66: 45 | AB66: 42249 | AE66: 22.22 | AF66: 42586 | AI66: 150 | AJ66: 42507 | AK66: 9.6 | BG66: -8.8 | BH66: 42592 | BM66: 60.6 | BN66: 42592 | BQ66: 11.5 | BR66: 42592 | BS66: 45.274725 | BT66: 42592 | BU66: 19.78022 | BV66: 42592 | BW66: 16.483516 | BX66: 42592 | CA66: 36.2 | CB66: 42592
A67: 24 | B67: =VLOOKUP(A67,PlantMaterial!B:C,2,0) -> C04-1ESQ1 | C67: N+ | D67: 2 | E67: 04608 | F67: 3 | G67: 13 | H67: 136.5 | M67: 3.02 | N67: 42586 | S67: 9.63 | T67: 42592 | U67: 13.5 | V67: 42586 | Y67: 3.87498 | Z67: 42592 | AA67: 45 | AB67: 42249 | AE67: 22.27 | AF67: 42586 | AI67: 135 | AJ67: 42507 | AK67: 9.4 | BG67: -9.2 | BH67: 42592 | BM67: 60.2 | BN67: 42592 | BQ67: 11 | BR67: 42592 | BS67: 47.472527 | BT67: 42592 | BU67: 19.120879 | BV67: 42592 | BW67: 13.516484 | BX67: 42592 | CA67: 36.3 | CB67: 42592
A68: 25 | B68: =VLOOKUP(A68,PlantMaterial!B:C,2,0) -> MONTEGO | C68: N+ | D68: 2 | E68: 04616 | F68: 5 | G68: 14 | H68: 147 | M68: 3.03 | N68: 42586 | S68: 9.16 | T68: 42592 | U68: 13.5 | V68: 42586 | Y68: 4.32814 | Z68: 42592 | AA68: 45 | AB68: 42249 | AE68: 22.31 | AF68: 42586 | AI68: 135 | AJ68: 42507 | AK68: 9.5 | BG68: -8.9 | BH68: 42592 | BM68: 60 | BN68: 42592 | BQ68: 11.7 | BR68: 42592 | BS68: 45.054945 | BT68: 42592 | BU68: 21.318681 | BV68: 42592 | BW68: 17.582418 | BX68: 42592 | CA68: 38.8 | CB68: 42592
A69: 26 | B69: =VLOOKUP(A69,PlantMaterial!B:C,2,0) -> RAPSO_304 | C69: N+ | D69: 2 | E69: 04591 | F69: 4 | G69: 10 | H69: 105 | M69: 4.1 | N69: 42586 | S69: 13.3 | T69: 42592 | U69: 13.5 | V69: 42586 | Y69: 4.88916 | Z69: 42592 | AA69: 45 | AB69: 42249 | AE69: 30.18 | AF69: 42586 | AI69: 150 | AJ69: 42507 | AK69: 9.6 | BG69: -11.6 | BH69: 42592 | BM69: 62.9 | BN69: 42592 | BQ69: 9.6 | BR69: 42592 | BS69: 48.461538 | BT69: 42592 | BU69: 17.802198 | BV69: 42592 | BW69: 14.065934 | BX69: 42592 | CA69: 34.4 | CB69: 42592
A70: 27 | B70: =VLOOKUP(A70,PlantMaterial!B:C,2,0) -> TENOR | C70: N+ | D70: 2 | E70: 04592 | F70: 5 | G70: 10 | H70: 105 | M70: 2.72 | N70: 42586 | S70: 8.59 | T70: 42592 | U70: 13.5 | V70: 42586 | Y70: 3.6491 | Z70: 42592 | AA70: 45 | AB70: 42249 | AE70: 20.05 | AF70: 42586 | AI70: 150 | AJ70: 42507 | AK70: 9.4 | BG70: -9.6 | BH70: 42592 | BM70: 59.3 | BN70: 42592 | BQ70: 11.8 | BR70: 42592 | BS70: 47.032967 | BT70: 42592 | BU70: 20 | BV70: 42592 | BW70: 18.351648 | BX70: 42592 | CA70: 37.7 | CB70: 42592
A71: 28 | B71: =VLOOKUP(A71,PlantMaterial!B:C,2,0) -> LEL17 | C71: N+ | D71: 2 | E71: 04576 | F71: 1 | G71: 8 | H71: 84 | M71: 3.81 | N71: 42586 | S71: 12.09 | T71: 42592 | U71: 13.5 | V71: 42586 | Y71: 4.61835 | Z71: 42592 | AA71: 45 | AB71: 42249 | AE71: 27.99 | AF71: 42586 | AI71: 130 | AJ71: 42507 | AK71: 9.7 | BG71: -10.2 | BH71: 42592 | BM71: 62.4 | BN71: 42592 | BQ71: 10.1 | BR71: 42592 | BS71: 47.472527 | BT71: 42592 | BU71: 18.131868 | BV71: 42592 | BW71: 14.395604 | BX71: 42592 | CA71: 34.4 | CB71: 42592
A72: 29 | B72: =VLOOKUP(A72,PlantMaterial!B:C,2,0) -> EXPRESS | C72: N+ | D72: 2 | E72: 04599 | F72: 6 | G72: 11 | H72: 115.5 | I72: 42 | J72: 42430 | M72: 2.37 | N72: 42586 | S72: 7.15 | T72: 42592 | U72: 13.5 | V72: 42586 | Y72: 3.18786 | Z72: 42592 | AA72: 45 | AB72: 42249 | AE72: 17.42 | AF72: 42586 | AI72: 140 | AJ72: 42507 | AK72: 9.7 | BG72: -7.8 | BH72: 42592 | BM72: 60.1 | BN72: 42592 | BQ72: 11 | BR72: 42592 | BS72: 45.054945 | BT72: 42592 | BU72: 20.10989 | BV72: 42592 | BW72: 18.791209 | BX72: 42592 | CA72: 36.6 | CB72: 42592
A73: 30 | B73: =VLOOKUP(A73,PlantMaterial!B:C,2,0) -> C04-1LEQ0 | C73: N+ | D73: 2 | E73: 04605 | F73: 6 | G73: 12 | H73: 126 | M73: 2.97 | N73: 42586 | S73: 9.52 | T73: 42592 | U73: 13.5 | V73: 42586 | Y73: 3.67584 | Z73: 42592 | AA73: 45 | AB73: 42249 | AE73: 21.88 | AF73: 42586 | AI73: 150 | AJ73: 42507 | AK73: 9.5 | BG73: -9 | BH73: 42592 | BM73: 62.5 | BN73: 42592 | BQ73: 10.2 | BR73: 42592 | BS73: 47.802198 | BT73: 42592 | BU73: 18.461538 | BV73: 42592 | BW73: 15.714286 | BX73: 42592 | CA73: 35.4 | CB73: 42592
A74: 31 | B74: =VLOOKUP(A74,PlantMaterial!B:C,2,0) -> C04-1LEQ1 | C74: N+ | D74: 2 | E74: 04579 | F74: 4 | G74: 8 | H74: 84 | M74: 3.28 | N74: 42586 | S74: 10.4 | T74: 42592 | U74: 13.5 | V74: 42586 | Y74: 4.01388 | Z74: 42592 | AA74: 45 | AB74: 42249 | AE74: 24.18 | AF74: 42586 | AI74: 130 | AJ74: 42507 | AK74: 9.4 | BG74: -10 | BH74: 42592 | BM74: 62.3 | BN74: 42592 | BQ74: 9.8 | BR74: 42592 | BS74: 47.252747 | BT74: 42592 | BU74: 18.241758 | BV74: 42592 | BW74: 13.956044 | BX74: 42592 | CA74: 34.6 | CB74: 42592
A75: 32 | B75: =VLOOKUP(A75,PlantMaterial!B:C,2,0) -> A05-1LEQ0 | C75: N+ | D75: 2 | E75: 04582 | F75: 1 | G75: 9 | H75: 94.5 | M75: 3.92 | N75: 42586 | S75: 12.25 | T75: 42592 | U75: 13.5 | V75: 42586 | Y75: 4.86889 | Z75: 42592 | AA75: 45 | AB75: 42249 | AE75: 28.81 | AF75: 42586 | AI75: 155 | AJ75: 42507 | AK75: 9.7 | BG75: -10.2 | BH75: 42592 | BM75: 62.7 | BN75: 42592 | BQ75: 9.9 | BR75: 42592 | BS75: 46.703297 | BT75: 42592 | BU75: 18.571429 | BV75: 42592 | BW75: 15.714286 | BX75: 42592 | CA75: 34.9 | CB75: 42592
A76: 33 | B76: =VLOOKUP(A76,PlantMaterial!B:C,2,0) -> A05-1LEQ1 | C76: N+ | D76: 2 | E76: 04604 | F76: 5 | G76: 12 | H76: 126 | M76: 4.61 | N76: 42586 | S76: 14.6 | T76: 42592 | U76: 13.5 | V76: 42586 | Y76: 5.73924 | Z76: 42592 | AA76: 45 | AB76: 42249 | AE76: 33.96 | AF76: 42586 | AI76: 140 | AJ76: 42507 | AK76: 9.5 | BG76: -8.2 | BH76: 42592 | BM76: 62.7 | BN76: 42592 | BQ76: 10.1 | BR76: 42592 | BS76: 47.252747 | BT76: 42592 | BU76: 18.571429 | BV76: 42592 | BW76: 15.714286 | BX76: 42592 | CA76: 35.2 | CB76: 42592
A77: 34 | B77: =VLOOKUP(A77,PlantMaterial!B:C,2,0) -> RAPSO_4 | C77: N+ | D77: 2 | E77: 04581 | F77: 6 | G77: 8 | H77: 84 | M77: 2.99 | N77: 42586 | S77: 9.53 | T77: 42592 | U77: 13.5 | V77: 42586 | Y77: 3.696 | Z77: 42592 | AA77: 45 | AB77: 42249 | AE77: 22 | AF77: 42586 | AI77: 130 | AJ77: 42507 | AK77: 9.6 | BG77: -9.2 | BH77: 42592 | BM77: 63.3 | BN77: 42592 | BQ77: 10.2 | BR77: 42592 | BS77: 47.582418 | BT77: 42592 | BU77: 18.461538 | BV77: 42592 | BW77: 13.406593 | BX77: 42592 | CA77: 35.3 | CB77: 42592
A78: 35 | B78: =VLOOKUP(A78,PlantMaterial!B:C,2,0) -> C04-1MASQ0 | C78: N+ | D78: 2 | E78: 04584 | F78: 3 | G78: 9 | H78: 94.5 | M78: 3.82 | N78: 42586 | S78: 12.35 | T78: 42592 | U78: 13.5 | V78: 42586 | Y78: 4.70773 | Z78: 42592 | AA78: 45 | AB78: 42249 | AE78: 28.19 | AF78: 42586 | AI78: 145 | AJ78: 42507 | AK78: 9.4 | BG78: -8 | BH78: 42592 | BM78: 64 | BN78: 42592 | BQ78: 9.8 | BR78: 42592 | BS78: 48.131868 | BT78: 42592 | BU78: 18.351648 | BV78: 42592 | BW78: 13.736264 | BX78: 42592 | CA78: 35.4 | CB78: 42592
A79: 36 | B79: =VLOOKUP(A79,PlantMaterial!B:C,2,0) -> C04-1MASQ1 | C79: N+ | D79: 2 | E79: 04596 | F79: 3 | G79: 11 | H79: 115.5 | M79: 2.69 | N79: 42586 | S79: 8.41 | T79: 42592 | U79: 13.5 | V79: 42586 | Y79: 3.42886 | Z79: 42592 | AA79: 45 | AB79: 42249 | AE79: 19.82 | AF79: 42586 | AI79: 140 | AJ79: 42507 | AK79: 9.5 | BG79: -7.9 | BH79: 42592 | BM79: 62 | BN79: 42592 | BQ79: 10.6 | BR79: 42592 | BS79: 46.593407 | BT79: 42592 | BU79: 19.010989 | BV79: 42592 | BW79: 14.285714 | BX79: 42592 | CA79: 35.6 | CB79: 42592
A80: 37 | B80: =VLOOKUP(A80,PlantMaterial!B:C,2,0) -> RAPSO_323 | C80: N+ | D80: 2 | E80: 04580 | F80: 5 | G80: 8 | H80: 84 | M80: 3.37 | N80: 42586 | S80: 10.52 | T80: 42592 | U80: 13.5 | V80: 42586 | Y80: 4.216 | Z80: 42592 | AA80: 45 | AB80: 42249 | AE80: 24.8 | AF80: 42586 | AI80: 150 | AJ80: 42507 | AK80: 9.6 | BG80: -11.3 | BH80: 42592 | BM80: 61.7 | BN80: 42592 | BQ80: 10.6 | BR80: 42592 | BS80: 46.593407 | BT80: 42592 | BU80: 18.681319 | BV80: 42592 | BW80: 12.857143 | BX80: 42592 | CA80: 35 | CB80: 42592
A81: 38 | B81: =VLOOKUP(A81,PlantMaterial!B:C,2,0) -> C04-1RAGTQ0 | C81: N+ | D81: 2 | E81: 04585 | F81: 4 | G81: 9 | H81: 94.5 | M81: 3.18 | N81: 42586 | S81: 10.22 | T81: 42592 | U81: 13.5 | V81: 42586 | Y81: 3.91448 | Z81: 42592 | AA81: 45 | AB81: 42249 | AE81: 23.44 | AF81: 42586 | AI81: 155 | AJ81: 42507 | AK81: 9.5 | BG81: -9.4 | BH81: 42592 | BM81: 61.7 | BN81: 42592 | BQ81: 10 | BR81: 42592 | BS81: 47.912088 | BT81: 42592 | BU81: 18.351648 | BV81: 42592 | BW81: 13.516484 | BX81: 42592 | CA81: 35.2 | CB81: 42592
A82: 39 | B82: =VLOOKUP(A82,PlantMaterial!B:C,2,0) -> C04-1RAGTQ1 | C82: N+ | D82: 2 | E82: 04615 | F82: 4 | G82: 14 | H82: 147 | M82: 2.77 | N82: 42586 | S82: 8.7 | T82: 42592 | U82: 13.5 | V82: 42586 | Y82: 3.51052 | Z82: 42592 | AA82: 45 | AB82: 42249 | AE82: 20.41 | AF82: 42586 | AI82: 150 | AJ82: 42507 | AK82: 9.5 | BG82: -7.1 | BH82: 42592 | BM82: 61.9 | BN82: 42592 | BQ82: 10.7 | BR82: 42592 | BS82: 46.813187 | BT82: 42592 | BU82: 18.901099 | BV82: 42592 | BW82: 13.626374 | BX82: 42592 | CA82: 35.6 | CB82: 42592
A83: 40 | B83: =VLOOKUP(A83,PlantMaterial!B:C,2,0) -> RAPSO_325 | C83: N+ | D83: 2 | E83: 04578 | F83: 3 | G83: 8 | H83: 84 | M83: 4.71 | N83: 42586 | S83: 14.97 | T83: 42592 | U83: 13.5 | V83: 42586 | Y83: 5.9092 | Z83: 42592 | AA83: 45 | AB83: 42249 | AE83: 34.76 | AF83: 42586 | AI83: 130 | AJ83: 42507 | AK83: 9.3 | BG83: -7.7 | BH83: 42592 | BM83: 62.9 | BN83: 42592 | BQ83: 10.8 | BR83: 42592 | BS83: 47.362637 | BT83: 42592 | BU83: 18.681319 | BV83: 42592 | BW83: 14.945055 | BX83: 42592 | CA83: 35.4 | CB83: 42592
A84: 41 | B84: =VLOOKUP(A84,PlantMaterial!B:C,2,0) -> C04-1SYNQ0 | C84: N+ | D84: 2 | E84: 04588 | F84: 1 | G84: 10 | H84: 105 | M84: 3.45 | N84: 42586 | S84: 11.01 | T84: 42592 | U84: 13.5 | V84: 42586 | Y84: 4.1656 | Z84: 42592 | AA84: 45 | AB84: 42249 | AE84: 25.4 | AF84: 42586 | AI84: 150 | AJ84: 42507 | AK84: 9.6 | BG84: -8.2 | BH84: 42592 | BM84: 62.8 | BN84: 42592 | BQ84: 10.1 | BR84: 42592 | BS84: 47.692308 | BT84: 42592 | BU84: 18.021978 | BV84: 42592 | BW84: 14.285714 | BX84: 42592 | CA84: 34.5 | CB84: 42592
A85: 42 | B85: =VLOOKUP(A85,PlantMaterial!B:C,2,0) -> C04-1SYNQ1 | C85: N+ | D85: 2 | E85: 04595 | F85: 2 | G85: 11 | H85: 115.5 | M85: 3.77 | N85: 42586 | S85: 12.08 | T85: 42592 | U85: 13.5 | V85: 42586 | Y85: 4.66704 | Z85: 42592 | AA85: 45 | AB85: 42249 | AE85: 27.78 | AF85: 42586 | AI85: 140 | AJ85: 42507 | AK85: 9.5 | BG85: -8.2 | BH85: 42592 | BM85: 61.4 | BN85: 42592 | BQ85: 10.8 | BR85: 42592 | BS85: 47.802198 | BT85: 42592 | BU85: 18.461538 | BV85: 42592 | BW85: 17.472527 | BX85: 42592 | CA85: 35.3 | CB85: 42592
A86: 1 | B86: =VLOOKUP(A86,PlantMaterial!B:C,2,0) -> AVISO | C86: N+ | D86: 3 | E86: used for INN | F86: 5 | G86: 21 | H86: 220.5 | I86: 33 | J86: 42430 | M86: 2.63 | N86: 42586 | S86: 8.02 | T86: 42592 | U86: 13.5 | V86: 42586 | Y86: 3.3003 | Z86: 42592 | AA86: 45 | AB86: 42249 | AE86: 19.3 | AF86: 42586 | AI86: 150 | AJ86: 42507 | AK86: 9.8 | BG86: -9.5 | BH86: 42592 | BM86: 59.6 | BN86: 42592 | BQ86: 11.7 | BR86: 42592 | BS86: 45.604396 | BT86: 42592 | BU86: 18.791209 | BV86: 42592 | BW86: 15.604396 | BX86: 42592 | CA86: 34.6 | CB86: 42592
A87: 2 | B87: =VLOOKUP(A87,PlantMaterial!B:C,2,0) -> A05-AMQ0 | C87: N+ | D87: 3 | E87: 04626 | F87: 3 | G87: 16 | H87: 168 | M87: 3.21 | N87: 42586 | S87: 9.83 | T87: 42592 | U87: 13.5 | V87: 42586 | Y87: 4.29702 | Z87: 42592 | AA87: 45 | AB87: 42249 | AE87: 23.61 | AF87: 42586 | AI87: 140 | AJ87: 42507 | AK87: 9.6 | BG87: -9.9 | BH87: 42592 | BM87: 59.5 | BN87: 42592 | BQ87: 11.8 | BR87: 42592 | BS87: 45.714286 | BT87: 42592 | BU87: 20 | BV87: 42592 | BW87: 14.835165 | BX87: 42592 | CA87: 36.8 | CB87: 42592
A88: 3 | B88: =VLOOKUP(A88,PlantMaterial!B:C,2,0) -> MONTEGO | C88: N+ | D88: 3 | E88: used for INN | F88: 3 | G88: 21 | H88: 220.5 | M88: 2.77 | N88: 42586 | S88: 8.49 | T88: 42592 | U88: 13.5 | V88: 42586 | Y88: 3.5552 | Z88: 42592 | AA88: 45 | AB88: 42249 | AE88: 20.2 | AF88: 42586 | AI88: 140 | AJ88: 42507 | AK88: 10.4 | BG88: -8.4 | BH88: 42592 | BM88: 61.1 | BN88: 42592 | BQ88: 10.6 | BR88: 42592 | BS88: 46.153846 | BT88: 42592 | BU88: 19.340659 | BV88: 42592 | BW88: 15.164835 | BX88: 42592 | CA88: 36 | CB88: 42592
A89: 4 | B89: =VLOOKUP(A89,PlantMaterial!B:C,2,0) -> A05-AMQ1 | C89: N+ | D89: 3 | E89: 04627 | F89: 4 | G89: 16 | H89: 168 | M89: 3.4 | N89: 42586 | S89: 10.44 | T89: 42592 | U89: 13.5 | V89: 42586 | Y89: 4.53043 | Z89: 42592 | AA89: 45 | AB89: 42249 | AE89: 25.03 | AF89: 42586 | AI89: 140 | AJ89: 42507 | AK89: 9.6 | BG89: -8.7 | BH89: 42592 | BM89: 59.9 | BN89: 42592 | BQ89: 11.5 | BR89: 42592 | BS89: 45.824176 | BT89: 42592 | BU89: 19.89011 | BV89: 42592 | BW89: 18.241758 | BX89: 42592 | CA89: 36.7 | CB89: 42592
A90: 5 | B90: =VLOOKUP(A90,PlantMaterial!B:C,2,0) -> TENOR | C90: N+ | D90: 3 | E90: used for INN | F90: 2 | G90: 17 | H90: 178.5 | M90: 1.97 | N90: 42586 | S90: 6.16 | T90: 42592 | U90: 13.5 | V90: 42586 | Y90: 2.65167 | Z90: 42592 | AA90: 45 | AB90: 42249 | AE90: 14.49 | AF90: 42586 | AI90: 145 | AJ90: 42507 | AK90: 9.6 | BG90: -10.5 | BH90: 42592 | BM90: 60 | BN90: 42592 | BQ90: 11.3 | BR90: 42592 | BS90: 46.703297 | BT90: 42592 | BU90: 20.10989 | BV90: 42592 | BW90: 19.78022 | BX90: 42592 | CA90: 37.6 | CB90: 42592
A91: 6 | B91: =VLOOKUP(A91,PlantMaterial!B:C,2,0) -> C03-AMQ0 | C91: N+ | D91: 3 | E91: 04648 | F91: 1 | G91: 20 | H91: 210 | M91: 2.74 | N91: 42586 | S91: 8.37 | T91: 42592 | U91: 13.5 | V91: 42586 | Y91: 3.78444 | Z91: 42592 | AA91: 45 | AB91: 42249 | AE91: 20.13 | AF91: 42586 | AI91: 140 | AJ91: 42507 | AK91: 9.7 | BG91: -8.6 | BH91: 42592 | BM91: 59.6 | BN91: 42592 | BQ91: 11.8 | BR91: 42592 | BS91: 45.714286 | BT91: 42592 | BU91: 20.659341 | BV91: 42592 | BW91: 16.593407 | BX91: 42592 | CA91: 38 | CB91: 42592
A92: 7 | B92: =VLOOKUP(A92,PlantMaterial!B:C,2,0) -> EXPRESS | C92: N+ | D92: 3 | E92: used for INN | F92: 1 | G92: 16 | H92: 168 | M92: 2.3 | N92: 42586 | S92: 7.08 | T92: 42592 | U92: 13.5 | V92: 42586 | Y92: 2.96736 | Z92: 42592 | AA92: 45 | AB92: 42249 | AE92: 16.86 | AF92: 42586 | AI92: 140 | AJ92: 42507 | AK92: 9.9 | BG92: -7.5 | BH92: 42592 | BM92: 62.7 | BN92: 42592 | BQ92: 10.2 | BR92: 42592 | BS92: 46.153846 | BT92: 42592 | BU92: 19.340659 | BV92: 42592 | BW92: 16.483516 | BX92: 42592 | CA92: 36 | CB92: 42592
A93: 8 | B93: =VLOOKUP(A93,PlantMaterial!B:C,2,0) -> C03-AMQ1 | C93: N+ | D93: 3 | E93: 04634 | F93: 5 | G93: 17 | H93: 178.5 | M93: 3.68 | N93: 42586 | S93: 11.36 | T93: 42592 | U93: 13.5 | V93: 42586 | Y93: 4.9051 | Z93: 42592 | AA93: 45 | AB93: 42249 | AE93: 27.1 | AF93: 42586 | AI93: 150 | AJ93: 42507 | AK93: 9.5 | BG93: -10.1 | BH93: 42592 | BM93: 59.4 | BN93: 42592 | BQ93: 11.7 | BR93: 42592 | BS93: 46.043956 | BT93: 42592 | BU93: 19.89011 | BV93: 42592 | BW93: 15.164835 | BX93: 42592 | CA93: 36.8 | CB93: 42592
A94: 9 | B94: =VLOOKUP(A94,PlantMaterial!B:C,2,0) -> C04-DKQ0 | C94: N+ | D94: 3 | E94: 04654 | F94: 1 | G94: 21 | H94: 220.5 | M94: 2.63 | N94: 42586 | S94: 8.03 | T94: 42592 | U94: 13.5 | V94: 42586 | Y94: 3.53922 | Z94: 42592 | AA94: 45 | AB94: 42249 | AE94: 19.34 | AF94: 42586 | AI94: 140 | AJ94: 42507 | AK94: 9.7 | BG94: -8.7 | BH94: 42592 | BM94: 60.1 | BN94: 42592 | BQ94: 11.6 | BR94: 42592 | BS94: 45.604396 | BT94: 42592 | BU94: 20.10989 | BV94: 42592 | BW94: 16.703297 | BX94: 42592 | CA94: 37 | CB94: 42592
A95: 10 | B95: =VLOOKUP(A95,PlantMaterial!B:C,2,0) -> C04-DKQ1 | C95: N+ | D95: 3 | E95: 04619 | F95: 2 | G95: 15 | H95: 157.5 | M95: 2.89 | N95: 42586 | S95: 9 | T95: 42592 | U95: 13.5 | V95: 42586 | Y95: 3.85168 | Z95: 42592 | AA95: 45 | AB95: 42249 | AE95: 21.28 | AF95: 42586 | AI95: 150 | AJ95: 42507 | AK95: 9.6 | BG95: -6.3 | BH95: 42592 | BM95: 61.6 | BN95: 42592 | BQ95: 10.7 | BR95: 42592 | BS95: 46.483516 | BT95: 42592 | BU95: 19.89011 | BV95: 42592 | BW95: 17.582418 | BX95: 42592 | CA95: 37.1 | CB95: 42592
A96: 11 | B96: =VLOOKUP(A96,PlantMaterial!B:C,2,0) -> AM087 | C96: N+ | D96: 3 | E96: 04643 | F96: 2 | G96: 19 | H96: 199.5 | M96: 4.05 | N96: 42586 | S96: 12.83 | T96: 42592 | U96: 13.5 | V96: 42586 | Y96: 5.14502 | Z96: 42592 | AA96: 45 | AB96: 42249 | AE96: 29.74 | AF96: 42586 | AI96: 155 | AJ96: 42507 | AK96: 9.8 | BG96: -9.2 | BH96: 42592 | BM96: 60.9 | BN96: 42592 | BQ96: 11.4 | BR96: 42592 | BS96: 47.362637 | BT96: 42592 | BU96: 19.010989 | BV96: 42592 | BW96: 19.010989 | BX96: 42592 | CA96: 36 | CB96: 42592
A97: 12 | B97: =VLOOKUP(A97,PlantMaterial!B:C,2,0) -> AVISO | C97: N+ | D97: 3 | E97: 04641 | F97: 6 | G97: 18 | H97: 189 | M97: 2.86 | N97: 42586 | S97: 8.91 | T97: 42592 | U97: 13.5 | V97: 42586 | Y97: 3.6627 | Z97: 42592 | AA97: 45 | AB97: 42249 | AE97: 21.05 | AF97: 42586 | AI97: 135 | AJ97: 42507 | AK97: 9.6 | BG97: -9 | BH97: 42592 | BM97: 59.5 | BN97: 42592 | BQ97: 11.8 | BR97: 42592 | BS97: 46.483516 | BT97: 42592 | BU97: 19.120879 | BV97: 42592 | BW97: 17.912088 | BX97: 42592 | CA97: 35.8 | CB97: 42592
A98: 13 | B98: =VLOOKUP(A98,PlantMaterial!B:C,2,0) -> AM109 | C98: N+ | D98: 3 | E98: 04659 | F98: 6 | G98: 21 | H98: 220.5 | M98: 4.09 | N98: 42586 | S98: 12.75 | T98: 42592 | U98: 13.5 | V98: 42586 | Y98: 5.20038 | Z98: 42592 | AA98: 45 | AB98: 42249 | AE98: 30.06 | AF98: 42586 | AI98: 150 | AJ98: 42507 | AK98: 9.7 | BG98: -8.6 | BH98: 42592 | BM98: 59.7 | BN98: 42592 | BQ98: 11.6 | BR98: 42592 | BS98: 46.593407 | BT98: 42592 | BU98: 19.010989 | BV98: 42592 | BW98: 13.626374 | BX98: 42592 | CA98: 35.5 | CB98: 42592
A99: 14 | B99: =VLOOKUP(A99,PlantMaterial!B:C,2,0) -> MONTEGO | C99: N+ | D99: 3 | E99: 04636 | F99: 1 | G99: 18 | H99: 189 | I99: 32 | J99: 42430 | M99: 2.88 | N99: 42586 | S99: 9.08 | T99: 42592 | U99: 13.5 | V99: 42586 | Y99: 3.85476 | Z99: 42592 | AA99: 45 | AB99: 42249 | AE99: 21.18 | AF99: 42586 | AI99: 155 | AJ99: 42507 | AK99: 9.7 | BG99: -7.2 | BH99: 42592 | BM99: 60.8 | BN99: 42592 | BQ99: 10.5 | BR99: 42592 | BS99: 47.142857 | BT99: 42592 | BU99: 20 | BV99: 42592 | BW99: 14.945055 | BX99: 42592 | CA99: 37.7 | CB99: 42592
A100: 15 | B100: =VLOOKUP(A100,PlantMaterial!B:C,2,0) -> DK038 | C100: N+ | D100: 3 | E100: 04657 | F100: 4 | G100: 21 | H100: 220.5 | M100: 2.93 | N100: 42586 | S100: 9.27 | T100: 42592 | U100: 13.5 | V100: 42586 | Y100: 3.73507 | Z100: 42592 | AA100: 45 | AB100: 42249 | AE100: 21.59 | AF100: 42586 | AI100: 140 | AJ100: 42507 | AK100: 9.5 | BG100: -6.8 | BH100: 42592 | BM100: 61.3 | BN100: 42592 | BQ100: 10.4 | BR100: 42592 | BS100: 47.142857 | BT100: 42592 | BU100: 19.010989 | BV100: 42592 | BW100: 14.175824 | BX100: 42592 | CA100: 36 | CB100: 42592
...

Sheet Files
A1: FileName | B1: Link | C1: FileType | D1: FileSize | E1: CreationDate | F1: Description
A2: Meteo_data | B2: See tab | C2: Excel
A3: Soil_data | B3: See tab | C3: Excel
A4: INN_data | B4: See tab | C4: Excel
A5: Parcellaire_data | B5: See tab | C5: Excel
A6: ITK_data | B6: See tab | C6: Excel

Sheet ForestComplementaryInfo
A1: TrialType | B1: TrialStatus | C1: DataFormat

Sheet StaticData
A1: TaxonScientificName | B1: InstitutionName | C1: HoldingInstitution | D1: ProjectAcronym | E1: SiteName
A2: Acareosperma Gagnep. | B2: A & I University | C2: Conservatoire Botanique National Méditerranéen de Porquerolles | D2: AF 1999 018 | E2: Arvalis-Chalons
A3: Acareosperma spireanum Gagnep. | B3: Abed Plant Breeding Station | C3: Gautier Semences | D3: AF 1999 046 | E3: Arvalis-Greoux
A4: Acyrthosiphon magnoliae | B4: Abteilung Biochemie | C4: Institut Jean-Pierre Bourgin | D4: AF 1999 064 | E4: Bergheim
A5: Acyrthosiphon pisum | B5: Abteilung Traub | C5: Pépinière du Mas d'Auge | D5: AF 2001 001 | E5: BGAMDV
A6: Aegilops | B6: ADIS DNA core facility at MPIZ | C6: Pépinières Rey | D6: AF 2001 009 | E6: Bordeaux
A7: Aegilops aucheri Boiss. | B7: ADT | C7: UE Ressources Génétiques végétales en Conditions Océaniques, INRA-Rennes, Site de Ploudaniel | D7: AF 2001 019-031 | E7: Clermont-Ferrand
A8: Aegilops bicornis | B8: Agricultural and Agri-Food Canada | C8: UMR Amélioration Génétique et Adaptation des Plantes, INRA-Montpellier | D8: AF 2001 024 | E8: Colmar
A9: Aegilops bicornis (Forsk.) Jaub. & Spach. | B9: Agricultural and Technological Research Centre | C9: UMR Développement et Amélioration des Plantes, INRA-Montpellier | D9: AF 2001 030 | E9: Dijon
A10: Aegilops comosa | B10: Agricultural Biotechnology R&D, Life Technologies, Inc. | C10: UMR Écophysiologie et Génomique Fonctionnelle de la Vigne, INRA-Bordeaux | D10: AF 2001 032 | E10: Estrees-Mons
A11: Aegilops comosa Sibth. & Sm. | B11: Agricultural Experiment Station University of the District of Columbia | C11: UMR Génétique, Diversité et Ecophysiologie des Céréales, INRA-Clermont | D11: AF 2001 047 | E11: Estrées-Mons
A12: Aegilops crassa Boiss. | B12: Agricultural Genomics | C12: UMR Génétique et Écophysiologie des Légumineuses à Graines, INRA-Dijon | D12: AF 2001 051 | E12: Fertreve - Foret de Vincence
... A21: Aegilops mutica Boiss. | B21: Agricultural Research Institute, Uyole | C21: URP Prairies et Plantes Fourragères, INRA-Lusignan | D21: AtPhy | E21: Reclainville
A22: Aegilops ovata L. | B22: Agricultural Research Organization Volcani Centre | D22: BcLTF1 | E22: Rennes
A23: Aegilops ovata var. anatolica Eig | B23: Agricultural Research Station - Ghana | D23: BCVEL1 | E23: Saint-Laurent - Foret domaniale de Vierzon
A24: Aegilops peregrina | B24: Agricultural Research Station - Greece | D24: BcYOH1 | E24: Saint-Symphorien - Foret domaniale de la Petite Charnie
A25: Aegilops recta | B25: Agricultural Research Station Lovrin-Timis | D25: BerrySize
A26: Aegilops searsii Feldman & Kislev | B26: Agriculture & Animal Production State Research Farm | D26: BGI_EST_OS
A27: Aegilops sharonensis | B27: Agri-obtentions Clermont-Ferrand | D27: BIEP
A28: Aegilops speltoides | B28: Agri-Obtentions, Guyancourt | D28: BotPathoINRA
A29: Aegilops squarrosa auct., p. p., non. L. | B29: Agripro Seeds Inc. | D29: Botrytis_on_Sunflower_2008
A30: Aegilops squarrosa L. | B30: Agrogene | D30: B1
A31: Aegilops subulata Pomel | B31: Agrolit S.A. | D31: Cabomba_EST
A32: Aegilops tauschii | B32: Agronomy | D32: CANDIDATE_GENES_BIOGECO
A33: Aegilops tauschii subsp. tauschii x Triticum turgidum subsp. | B33: A.H. Whitmore Foundation Farm | D33: Chlorose
A34: Aegilops triuncialis L. | B34: Alata Horticultural Research Institute | D34: CI1999 076
A35: Aegilops turcomanica | B35: Alibert | D35: CI1999 088
A36: Aegilops variabilis Eig | B36: All-Union Institute for Vegetable Breeding and Seed Production | D36: CI2000 005
... A226: Citrus kotokan Hayata | B226: Chambre d'Agriculture du Loir-et-Cher | D226: Rapsodyn
A227: Citrus L. | B227: Chambre d'Agriculture du Lot
A228: Citrus latifolia Tan. | B228: Chambre d'Agriculture du Lot-et-Garonne
A229: Citrus latipes (Swing.) Tan. | B229: Chambre d'Agriculture du Maine-et-Loire
A230: Citrus leiocarpa Hort. ex Tan. | B230: Chambre d'Agriculture du Puy-de-Dôme
A231: Citrus limetta Risso | B231: Chambre d'Agriculture du Tarn
A232: Citrus limettioides Tan. | B232: Chambre d'Agriculture du Tarn-et-Garonne
A233: Citrus limon (L.) Burm. | B233: Chambre d'Agriculture du Var
A234: (Citrus limon (L.) Burm. x Citrus aurantifolia (Christm.) Swing.) | B234: Chambre d'Agriculture du Vaucluse
A235: (Citrus limon (L.) Burm. x Citrus reticulata Blanco) | B235: Chambre Régionale d'Agriculture d'Auvergne
A236: (Citrus limon (L.) Burm. x Citrus sinensis (L.) Osb.) | B236: Chaozhou Fruit Research Institute
A237: (Citrus limon (L.) Burm. x Fortunella sp.) | B237: Charlottetown Research Centre, Agriculture and Agri-Food Canada
A238: (Citrus limon (L.) Burm. x Poncirus trifoliata (L.) Raf.) | B238: Chiayi Agricultural Experiment Station
... A1457: Vitis vinifera subsp vinifera cv. Ben Suilah | B1457: ZMBP - Center for Molecular Biology of Plants
A1458: Vitis vinifera subsp vinifera cv. Beneti noir
A1459: Vitis vinifera subsp vinifera cv. Benicarlo
A1460: Vitis vinifera subsp vinifera cv. Beogradska rana
A1461: Vitis vinifera subsp vinifera cv. Béquignol
A1462: Vitis vinifera subsp vinifera cv. Béquignol blanc
A1463: Vitis vinifera subsp vinifera cv. Béquignol gris
A1464: Vitis vinifera subsp vinifera cv. Beran
A1465: Vitis vinifera subsp vinifera cv. Berbecel
A1466: Vitis vinifera subsp vinifera cv. Berdomenel
A1467: Vitis vinifera subsp vinifera cv. Beregi rozsas
A1468: Vitis vinifera subsp vinifera cv. Beregi rozsas faux
A1469: Vitis vinifera subsp vinifera cv. Bermestia bianca
... A5470: Zinnia elegans

Sheet Meteo_Data
A1: Nom de la demande
A2: Pas de temps
A3: Date de début
A4: Date de fin
A6: ___Temperature___ | B6: Mean | C6: température moyenne de la journée | H6: °C
B7: High | C7: température la plus élevée de la journée | H7: °C
B8: Low | C8: température la plus basse de la journée | H8: °C
A9: RH | B9: Mean | C9: humidité relative moyenne de la journée | H9: %
A10: Solar | B10: W/m2 | C10: rayonnement moyen de la journée | H10: wat/m2
A11: Wind | B11: Speed | C11: vitesse du vent moyen de la journée | H11: km/h
A12: Rain- | B12: Fall | C12: précipitation de la journée | H12: mm
A13: ET | B13: Ref | C13: évapotranspiration de référence | H13: mm
A14: ET | B14: Crop | C14: évapotranspiration calculée en fonction du coef choisi pour la culture, | H14: mm
A15: Irrig | B15: ation | C15: perte en eau de la journée | H15: mm
A16: Net | B16: Water | C16: cumul de la perte d'eau depuis le début du calcul d'ETP | H16: mm
A17: Cum | B17: Net
B19: ___Temperature___ | E19: RH | F19: Solar | G19: Wind | H19: Rain- | I19: ET | J19: ET | K19: Irrig | L19: Net | M19: Cum
A20: Date | B20: Mean | C20: High | D20: Low | E20: Mean | F20: W/m2 | G20: Speed | H20: Fall | I20: Ref | J20: Crop | K20: ation | L20: Water | M20: Net
A21: 01/07/2015 | B21: 27.8 | C21: 35.4 | D21: 19.4 | E21: 46 | F21: 7961 | G21: 2.8 | H21: 0 | I21: 8.1
A22: 02/07/2015 | B22: 23.6 | C22: 29 | D22: 19.2 | E22: 60 | F22: 6820 | G22: 2.6 | H22: 0.1 | I22: 5.9
A23: 03/07/2015 | B23: 25.8 | C23: 32 | D23: 18 | E23: 59 | F23: 7031 | G23: 2.4 | H23: 0 | I23: 6.2
A24: 04/07/2015 | B24: 24.6 | C24: 29.6 | D24: 22.7 | E24: 59 | F24: 6672 | G24: 2.6 | H24: 0.2 | I24: 6.1
A25: 05/07/2015 | B25: 18.9 | C25: 23.2 | D25: 17.6 | E25: 68 | F25: 4331 | G25: 2.2 | H25: 0.9 | I25: 3.7
A26: 06/07/2015 | B26: 20.1 | C26: 26.4 | D26: 13.7 | E26: 61 | F26: 7286 | G26: 1.3 | H26: 0 | I26: 5
A27: 07/07/2015 | B27: 19.7 | C27: 26 | D27: 16.2 | E27: 68 | F27: 5628 | G27: 2.9 | H27: 1.1 | I27: 5
A28: 08/07/2015 | B28: 16.5 | C28: 18.8 | D28: 13.7 | E28: 70 | F28: 3522 | G28: 4.9 | H28: 1.1 | I28: 3.3
A29: 09/07/2015 | B29: 16.1 | C29: 19.7 | D29: 13.5 | E29: 60 | F29: 6172 | G29: 2.3 | H29: 0 | I29: 4.2
A30: 10/07/2015 | B30: 18.6 | C30: 25 | D30: 10.5 | E30: 52 | F30: 8020 | G30: 2 | H30: 0 | I30: 5.5
A31: 11/07/2015 | B31: 19.2 | C31: 25.5 | D31: 13 | E31: 57 | F31: 7906 | G31: 2.9 | H31: 0 | I31: 5.8
A32: 12/07/2015 | B32: 16.9 | C32: 19.9 | D32: 12.7 | E32: 71 | F32: 3006 | G32: 2.5 | H32: 1.1 | I32: 2.8
... A91: 09/09/2015 | B91: 15.2 | C91: 20.4 | D91: 10.1 | E91: 70 | F91: 5294 | G91: 2.8 | H91: 0 | I91: 3.2
A92: 10/09/2015 | B92: 15.1 | C92: 20.5 | D92: 10.7 | E92: 61 | F92: 5308 | G92: 2.6 | H92: 0 | I92: 3.6 | K92: 20
A93: 11/09/2015 | B93: 15.8 | C93: 20.8 | D93: 10.5 | E93: 64 | F93: 5094 | G93: 1.7 | H93: 0 | I93: 3
A94: 12/09/2015 | B94: 16 | C94: 19.5 | D94: 14.9 | E94: 77 | F94: 1803 | G94: 2.3 | H94: 3.1 | I94: 2.1
A95: 13/09/2015 | B95: 13.4 | C95: 17.5 | D95: 9.5 | E95: 93 | F95: 1222 | G95: 2.8 | H95: 9.6 | I95: 0.8
A96: 14/09/2015 | B96: 14 | C96: 16.8 | D96: 11.2 | E96: 76 | F96: 2653 | G96: 4.9 | H96: 9.4 | I96: 2.3
A97: 15/09/2015 | B97: 14 | C97: 17.7 | D97: 10.6 | E97: 69 | F97: 4717 | G97: 4.8 | H97: 4.1 | I97: 3.4
A98: 16/09/2015 | B98: 16.4 | C98: 19.6 | D98: 12.9 | E98: 79 | F98: 1819 | G98: 5.1 | H98: 11.3 | I98: 2.3
A99: 17/09/2015 | B99: 14.4 | C99: 17.2 | D99: 14.3 | E99: 77 | F99: 1953 | G99: 3.7 | H99: 0.5 | I99: 2
A100: 18/09/2015 | B100: 13.1 | C100: 16.9 | D100: 10.4 | E100: 85 | F100: 2497 | G100: 3.4 | H100: 5.6 | I100: 1.7
A101: 19/09/2015 | B101: 13 | C101: 17.5 | D101: 10.9 | E101: 83 | F101: 2867 | G101: 2.4 | H101: 0.5 | I101: 1.9
A102: 20/09/2015 | B102: 13 | C102: 17.7 | D102: 7.5 | E102: 77 | F102: 4108 | G102: 0.8 | H102: 0 | I102: 1.9
A103: 21/09/2015 | B103: 13.9 | C103: 17.3 | D103: 8.8 | E103: 75 | F103: 3594 | G103: 2.6 | H103: 1.2 | I103: 2.2
A104: 22/09/2015 | B104: 12 | C104: 14.8 | D104: 11.7 | E104: 85 | F104: 2486 | G104: 4 | H104: 8.2 | I104: 1.7
... A432: 15/08/2016 | B432: 18.4 | C432: 23.6 | D432: 13 | E432: 71 | F432: 6664 | G432: 2.9 | H432: 0 | I432: 4.3

Sheet Soil_data
C2: Infos concernant la nature du sol, sa composition, sa profondeur...

Sheet INN_Data
A2: De "Parcelle" à "Genotype" = données générales sur l'essai
A3: Manip = quelle INN | L3: Ne mettre que les datas brutes
A4: Date = date de prélèvement
A5: Stade = stade moyen de la parcelle
A6: Deux échantillons différents sont identifiés : 1/5 des plantes et 4/5 des plantes
A7: A partir des INN3, une distinction est faite entre les feuilles et le tiges pour les pesées
A8: et les analyses par SAS pour l'échantillon 1/5
A9: Nbr = nombre de plantes du prélèvement
A10: MF = matière fraiche du prélèvement en grammes
A11: MS = matière séche du prélèvement en grammes
A12: N % DUMAS Spérial Ferti = pourcentage d'azote dans la plante (résultat laboratoire)
A14: INN = (Qté N tot / MS (1/5) (g)) / %Ncritique
A18: PARCELLES | B18: NB plantes total | C18: NB plantes (4/5) | D18: NB plantes (1/5) | E18: POIDS FRAIS - g (FEUILLE1) 06/04/2016 | F18: POIDS FRAIS 4/5 - g (FEUILLE1) 06/04/2016 | G18: POIDS FRAIS 1/5 - g (FEUILLE1) 06/04/2016 | H18: POIDS FRAIS - g (FEUILLE2) 06/04/2016 | I18: Delta FEUILLE1-FEUILLE2 | J18: echantillonnage (1/5) / (4/5) | K18: POIDS FRAIS FEUILLES - g | L18: POIDS FRAIS TIGE - g | M18: POIDS SEC 1/5 - g (FEUILLE3) 13/04/2016 | N18: taux humidité | O18: POIDS SEC FEUILLES - g | P18: POIDS SEC TIGE - g | Q18: INN | R18: N% moyen | S18: N% tige | T18: N% feuille | U18: REMARQUES PRELEVEMENTS | V18: SURFACE prélevée m² | W18: densité pl/m²
A19: PO1 R1 | B19: =C19+D19 -> 89 | C19: 75 | D19: 14 | E19: =F19+G19 -> 3750 | F19: 2900 | G19: 850 | H19: 838 | I19: 12 | J19: 0.22666667 | K19: 422 | L19: 416 | M19: =O19+P19 -> 94.2 | N19: =(H19-M19)/H19 -> 0.8875895 | O19: 57.3 | P19: 36.9 | Q19: =R19/(4.48*((E19*(1-N19))*(10000/2.25)/1000000)^(-0.25)) -> 1.4075921 | R19: 5.3900268 | S19: 4.922 | T19: 6.1168 | V19: 2.25 | W19: 39.555556
A20: PO1 R2 | B20: =C20+D20 -> 52 | C20: 41 | D20: 11 | E20: =F20+G20 -> 3750 | F20: 3000 | G20: 750 | H20: 756 | I20: -6 | J20: 0.2 | K20: 437 | L20: 319 | M20: =O20+P20 -> 93.5 | N20: =(H20-M20)/H20 -> 0.87632275 | O20: 59.6 | P20: 33.9 | Q20: =R20/(4.48*((E20*(1-N20))*(10000/2.25)/1000000)^(-0.25)) -> 1.2190934 | R20: 4.5580632 | S20: 4.3915 | T20: 4.8509 | V20: 2.25 | W20: 23.111111
A21: PO1 R3 | B21: =C21+D21 -> 71 | C21: 57 | D21: 14 | E21: =F21+G21 -> 3900 | F21: 2950 | G21: 950 | H21: 942 | I21: 8 | J21: 0.24358974 | K21: 535 | L21: 407 | M21: =O21+P21 -> 115 | N21: =(H21-M21)/H21 -> 0.87791932 | O21: 77.6 | P21: 37.4 | Q21: =R21/(4.48*((E21*(1-N21))*(10000/2.25)/1000000)^(-0.25)) -> 1.30716 | R21: 4.8553943 | S21: 4.6882 | T21: 5.2023 | V21: 2.25 | W21: 31.555556
A22: PO1 R4 | B22: =C22+D22 -> 82 | C22: 66 | D22: 16 | E22: =F22+G22 -> 5350 | F22: 3550 | G22: 1800 | H22: 1636 | I22: 164 | J22: 0.3364486 | K22: 172 (967) | L22: 275 (669) | M22: =O22+P22 -> 49.2 | N22: =(172+275-M22)/(172+275) -> 0.88993289 | O22: 24.5 | P22: 24.7 | Q22: =R22/(4.48*((E22*(1-N22))*(10000/2.25)/1000000)^(-0.25)) -> 1.1379224 | R22: 4.008053 | S22: 4.4519 | T22: 3.5678 | U22: seule une partie de l'échantillon a été conservé par erreur | V22: 2.25 | W22: 36.444444
A23: PO1 R5 | B23: =C23+D23 -> 64 | C23: 52 | D23: 12 | E23: =F23+G23 -> 3950 | F23: 2800 | G23: 1150 | H23: 1131 | I23: 19 | J23: 0.29113924 | K23: 675 | L23: 456 | M23: =O23+P23 -> 139.6 | N23: =(H23-M23)/H23 -> 0.87656941 | O23: 97.7 | P23: 41.9 | Q23: =R23/(4.48*((E23*(1-N23))*(10000/2.25)/1000000)^(-0.25)) -> 1.2329298 | R23: 4.5525739 | S23: 4.5653 | T23: 4.5229 | V23: 2.25 | W23: 28.444444
A24: PO1 R6 | B24: =C24+D24 -> 69 | C24: 55 | D24: 14 | E24: =F24+G24 -> 3350 | F24: 2550 | G24: 800 | H24: 779 | I24: 21 | J24: 0.23880597 | K24: 475 | L24: 304 | M24: =O24+P24 -> 95 | N24: =(H24-M24)/H24 -> 0.87804878 | O24: 63.4 | P24: 31.6 | Q24: =R24/(4.48*((E24*(1-N24))*(10000/2.25)/1000000)^(-0.25)) -> 1.3336402 | R24: 5.1470048 | S24: 4.9755 | T24: 5.4911 | V24: 2.25 | W24: 30.666667
A25: PO3 R1 | B25: =C25+D25 -> 63 | C25: 48 | D25: 15 | E25: =F25+G25 -> 2950 | F25: 2100 | G25: 850 | H25: 790 | I25: 60 | J25: 0.28813559 | K25: 480 | L25: 310 | M25: =O25+P25 -> 97.5 | N25: =(H25-M25)/H25 -> 0.87658228 | O25: 62.9 | P25: 34.6 | Q25: =R25/(4.48*((E25*(1-N25))*(10000/2.25)/1000000)^(-0.25)) -> 1.2023814 | R25: 4.7760185 | S25: 4.3012 | T25: 5.6392 | U25: échantillon FEUILLE2 issu de PO3 R1 4/5 | V25: 2.25 | W25: 28
A26: PO3 R2 | B26: =C26+D26 -> 74 | C26: 59 | D26: 15 | E26: =F26+G26 -> 4000 | F26: 2700 | G26: 1300 | H26: 1260 | I26: 40 | J26: 0.325 | K26: 708 | L26: 552 | M26: =O26+P26 -> 148.9 | N26: =(H26-M26)/H26 -> 0.8818254 | O26: 88.8 | P26: 60.1 | Q26: =R26/(4.48*((E26*(1-N26))*(10000/2.25)/1000000)^(-0.25)) -> 1.3449388 | R26: 5.0047238 | S26: 4.5925 | T26: 5.6138 | V26: 2.25 | W26: 32.888889
A27: PO3 R3 | B27: =C27+D27 -> 76 | C27: 60 | D27: 16 | E27: =F27+G27 -> 3500 | F27: 2350 | G27: 1150 | H27: 1114 | I27: 36 | J27: 0.32857143 | K27: 624 | L27: 490 | M27: =O27+P27 -> 138.2 | N27: =(H27-M27)/H27 -> 0.87594255 | O27: 88 | P27: 50.2 | Q27: =R27/(4.48*((E27*(1-N27))*(10000/2.25)/1000000)^(-0.25)) -> 1.2360884 | R27: 4.6984049 | S27: 4.3097 | T27: 5.3798 | V27: 2.25 | W27: 33.777778
A28: PO3 R4 | B28: =C28+D28 -> 67 | C28: 53 | D28: 14 | E28: =F28+G28 -> 5150 | F28: 3950 | G28: 1200 | H28: 1169 | I28: 31 | J28: 0.23300971 | K28: 577 | L28: 592 | M28: =O28+P28 -> 136.5 | N28: =(H28-M28)/H28 -> 0.88323353 | O28: 71.1 | P28: 65.4 | Q28: =R28/(4.48*((E28*(1-N28))*(10000/2.25)/1000000)^(-0.25)) -> 1.3802118 | R28: 4.8360196 | S28: 4.0815 | T28: 5.6563 | V28: 2.25 | W28: 29.777778
A29: PO3 R5 | B29: =C29+D29 -> 111 | C29: 90 | D29: 21 | E29: =F29+G29 -> 3250 | F29: 2400 | G29: 850 | H29: 809 | I29: 41 | J29: 0.26153846 | K29: 483 | L29: 326 | M29: =O29+P29 -> 108 | N29: =(H29-M29)/H29 -> 0.86650185 | O29: 64.6 | P29: 43.4 | Q29: =R29/(4.48*((E29*(1-N29))*(10000/2.25)/1000000)^(-0.25)) -> 1.2648019 | R29: 4.8084654 | S29: 4.4601 | T29: 5.327 | V29: 2.25 | W29: 49.333333
A30: PO3 R6 | B30: =C30+D30 -> 60 | C30: 49 | D30: 11 | E30: =F30+G30 -> 3550 | F30: 2450 | G30: 1100 | H30: 1077 | I30: 23 | J30: 0.30985915 | K30: 593 | L30: 484 | M30: =O30+P30 -> 121 | N30: =(H30-M30)/H30 -> 0.88765088 | O30: 75.9 | P30: 45.1 | Q30: =R30/(4.48*((E30*(1-N30))*(10000/2.25)/1000000)^(-0.25)) -> 1.1633448 | R30: 4.5168182 | S30: 4.0729 | T30: 5.2639 | V30: 2.25 | W30: 26.666667
A31: PO5 R1 | B31: =C31+D31 -> 21 | C31: 17 | D31: 4 | E31: =F31+G31 -> 2400 | F31: 2000 | G31: 400 | H31: 398 | I31: 2 | J31: 0.16666667 | K31: 232 | L31: 166 | M31: =O31+P31 -> 59.6 | N31: =(H31-M31)/H31 -> 0.85025126 | O31: 31.3 | P31: 28.3 | Q31: =R31/(4.48*((E31*(1-N31))*(10000/2.25)/1000000)^(-0.25)) -> 1.1847623 | R31: 4.7212963 | S31: 4.2439 | T31: 5.2493 | V31: 2.25 | W31: 9.3333333
A32: PO5 R2 | B32: =C32+D32 -> 32 | C32: 27 | D32: 5 | E32: =F32+G32 -> 4250 | F32: 3400 | G32: 850 | H32: 838 | I32: 12 | J32: 0.2 | K32: 442 | L32: 396 | M32: =O32+P32 -> 104.6 | N32: =(H32-M32)/H32 -> 0.875179 | O32: 58.4 | P32: 46.2 | Q32: =R32/(4.48*((E32*(1-N32))*(10000/2.25)/1000000)^(-0.25)) -> 1.262181 | R32: 4.5632698 | S32: 3.8761 | T32: 5.4319 | V32: 2.25 | W32: 14.222222
A33: PO5 R3 | B33: =C33+D33 -> 30 | C33: 23 | D33: 7 | E33: =F33+G33 -> 4100 | F33: 3450 | G33: 650 | H33: 640 | I33: 10 | J33: 0.15853659 | K33: 366 | L33: 274 | M33: =O33+P33 -> 65.6 | N33: =(H33-M33)/H33 -> 0.8975 | O33: 47.8 | P33: 17.8 | Q33: =R33/(4.48*((E33*(1-N33))*(10000/2.25)/1000000)^(-0.25)) -> 1.0711299 | R33: 4.1047704 | S33: 3.67 | T33: 5.2723 | V33: 2.25 | W33: 13.333333
A34: PO5 R4 | B34: =C34+D34 -> 26 | C34: 21 | D34: 5 | E34: =F34+G34 -> 4900 | F34: 3600 | G34: 1300 | H34: 1270 | I34: 30 | J34: 0.26530612 | K34: 558 | L34: 712 | M34: =O34+P34 -> 181.4 | N34: =(H34-M34)/H34 -> 0.85716535 | O34: 88.9 | P34: 92.5 | Q34: =R34/(4.48*((E34*(1-N34))*(10000/2.25)/1000000)^(-0.25)) -> 1.3166316 | R34: 4.4415085 | S34: 3.791 | T34: 5.0667 | V34: 2.25 | W34: 11.555556
A35: PO5 R5 | B35: =C35+D35 -> 40 | C35: 32 | D35: 8 | E35: =F35+G35 -> 4600 | F35: 3700 | G35: 900 | H35: 855 | I35: 45 | J35: 0.19565217 | K35: 431 | L35: 424 | M35: =O35+P35 -> 108.9 | N35: =(H35-M35)/H35 -> 0.87263158 | O35: 59.6 | P35: 49.3 | Q35: =R35/(4.48*((E35*(1-N35))*(10000/2.25)/1000000)^(-0.25)) -> 1.2880569 | R35: 4.5425926 | S35: 3.7542 | T35: 5.4957 | V35: 2.25 | W35: 17.777778
A36: PO5 R6 | B36: =C36+D36 -> 28 | C36: 22 | D36: 6 | E36: =F36+G36 -> 2450 | F36: 2050 | G36: 400 | H36: 366 | I36: 34 | J36: 0.16326531 | K36: 216 | L36: 150 | M36: =O36+P36 -> 47.8 | N36: =(H36-M36)/H36 -> 0.86939891 | O36: 31.3 | P36: 16.5 | Q36: =R36/(4.48*((E36*(1-N36))*(10000/2.25)/1000000)^(-0.25)) -> 1.0669583 | R36: 4.3771646 | S36: 3.7774 | T36: 5.5149 | V36: 2.25 | W36: 12.444444
A37: PO7 R1 | B37: =C37+D37 -> 65 | C37: 52 | D37: 13 | E37: =F37+G37 -> 4300 | F37: 3400 | G37: 900 | H37: 872 | I37: 28 | J37: 0.20930233 | K37: 507 | L37: 365 | M37: =O37+P37 -> 104.3 | N37: =(H37-M37)/H37 -> 0.88038991 | O37: 67.5 | P37: 36.8 | Q37: =R37/(4.48*((E37*(1-N37))*(10000/2.25)/1000000)^(-0.25)) -> 1.2811742 | R37: 4.667913 | S37: 4.3775 | T37: 5.2006 | V37: 2.25 | W37: 28.888889
... A42: PO7 R6 | B42: =C42+D42 -> 72 | C42: 56 | D42: 16 | E42: =F42+G42 -> 2900 | F42: 2250 | G42: 650 | H42: 644 | I42: 6 | J42: 0.22413793 | K42: 396 | L42: 248 | M42: =O42+P42 -> 81.9 | N42: =(H42-M42)/H42 -> 0.87282609 | O42: 56.3 | P42: 25.6 | Q42: =R42/(4.48*((E42*(1-N42))*(10000/2.25)/1000000)^(-0.25)) -> 1.1085509 | R42: 4.3891486 | S42: 4.0877 | T42: 5.0521 | V42: 2.25 | W42: 32

Sheet Parcellaire_data
F4: Le plan de l'essai avec les coordonnées X-Y correspondantes à celles de l'onglet "Data"
D13: R3 | E13: 21 | G13: PO-9 | H13: PO-28 | I13: PO-3 | J13: PO-15 | K13: PO-1 | L13: PO-13 | P13: PO-37 | Q13: PO-38 | R13: PO-39 | S13: PO-40 | T13: PO-41 | U13: PO-42 | W13: R4
E14: 20 | G14: PO-6 | H14: PO-29 | I14: PO-38 | J14: PO-25 | K14: PO-17 | L14: PO-22 | P14: PO-36 | Q14: PO-35 | R14: PO-34 | S14: PO-33 | T14: PO-32 | U14: PO-31
E15: 19 | G15: PO-24 | H15: PO-11 | I15: PO-31 | J15: PO-21 | K15: PO-42 | L15: PO-40 | P15: PO-25 | Q15: PO-26 | R15: PO-27 | S15: PO-28 | T15: PO-29 | U15: PO-30
E16: 18 | G16: PO-14 | H16: PO-19 | I16: PO-18 | J16: PO-34 | K16: PO-30 | L16: PO-12 | P16: PO-24 | Q16: PO-23 | R16: PO-22 | S16: PO-21 | T16: PO-20 | U16: PO-19
E17: 17 | G17: PO-41 | H17: PO-5 | I17: PO-37 | J17: PO-16 | K17: PO-8 | L17: PO-27 | P17: PO-13 | Q17: PO-14 | R17: PO-15 | S17: PO-16 | T17: PO-17 | U17: PO-18
E18: 16 | G18: PO-7 | H18: PO-26 | I18: PO-2 | J18: PO-4 | K18: PO-39 | L18: PO-23 | P18: PO-12 | Q18: PO-11 | R18: PO-10 | S18: PO-9 | T18: PO-8 | U18: PO-7
E19: 15 | G19: PO-36 | H19: PO-10 | I19: PO-20 | J19: PO-33 | K19: PO-35 | L19: PO-32 | P19: PO-1 | Q19: PO-2 | R19: PO-3 | S19: PO-4 | T19: PO-5 | U19: PO-6
D20: R2 | E20: 14 | G20: PO-1 | H20: PO-18 | I20: PO-12 | J20: PO-39 | K20: PO-25 | L20: PO-20 | P20: PO-1 | Q20: PO-18 | R20: PO-12 | S20: PO-39 | T20: PO-25 | U20: PO-20 | W20: R5
E21: 13 | G21: PO-5 | H21: PO-3 | I21: PO-24 | J21: PO-6 | K21: PO-4 | L21: PO-11 | P21: PO-5 | Q21: PO-3 | R21: PO-24 | S21: PO-6 | T21: PO-4 | U21: PO-11
E22: 12 | G22: PO-21 | H22: PO-10 | I22: PO-8 | J22: PO-22 | K22: PO-33 | L22: PO-30 | P22: PO-21 | Q22: PO-10 | R22: PO-8 | S22: PO-22 | T22: PO-33 | U22: PO-30
E23: 11 | G23: PO-9 | H23: PO-42 | I23: PO-36 | J23: PO-7 | K23: PO-15 | L23: PO-29 | P23: PO-9 | Q23: PO-42 | R23: PO-36 | S23: PO-7 | T23: PO-15 | U23: PO-29
E24: 10 | G24: PO-41 | H24: PO-16 | I24: PO-23 | J24: PO-26 | K24: PO-27 | L24: PO-17 | P24: PO-41 | Q24: PO-16 | R24: PO-23 | S24: PO-26 | T24: PO-27 | U24: PO-17
E25: 9 | G25: PO-32 | H25: PO-19 | I25: PO-35 | J25: PO-38 | K25: PO-14 | L25: PO-2 | P25: PO-32 | Q25: PO-19 | R25: PO-35 | S25: PO-38 | T25: PO-14 | U25: PO-2
E26: 8 | G26: PO-28 | H26: PO-13 | I26: PO-40 | J26: PO-31 | K26: PO-37 | L26: PO-34 | P26: PO-28 | Q26: PO-13 | R26: PO-40 | S26: PO-31 | T26: PO-37 | U26: PO-34
D27: R1 | E27: 7 | G27: PO-37 | H27: PO-38 | I27: PO-39 | J27: PO-40 | K27: PO-41 | L27: PO-42 | P27: PO-9 | Q27: PO-28 | R27: PO-3 | S27: PO-15 | T27: PO-1 | U27: PO-13 | W27: R6
E28: 6 | G28: PO-36 | H28: PO-35 | I28: PO-34 | J28: PO-33 | K28: PO-32 | L28: PO-31 | P28: PO-6 | Q28: PO-29 | R28: PO-38 | S28: PO-25 | T28: PO-17 | U28: PO-22
E29: 5 | G29: PO-25 | H29: PO-26 | I29: PO-27 | J29: PO-28 | K29: PO-29 | L29: PO-30 | P29: PO-24 | Q29: PO-11 | R29: PO-31 | S29: PO-21 | T29: PO-42 | U29: PO-40
E30: 4 | G30: PO-24 | H30: PO-23 | I30: PO-22 | J30: PO-21 | K30: PO-20 | L30: PO-19 | P30: PO-14 | Q30: PO-19 | R30: PO-18 | S30: PO-34 | T30: PO-30 | U30: PO-12
E31: 3 | G31: PO-13 | H31: PO-14 | I31: PO-15 | J31: PO-16 | K31: PO-17 | L31: PO-18 | P31: PO-41 | Q31: PO-5 | R31: PO-37 | S31: PO-16 | T31: PO-8 | U31: PO-27
E32: 2 | G32: PO-12 | H32: PO-11 | I32: PO-10 | J32: PO-9 | K32: PO-8 | L32: PO-7 | P32: PO-7 | Q32: PO-26 | R32: PO-2 | S32: PO-4 | T32: PO-39 | U32: PO-23
E33: 1 | G33: PO-1 | H33: PO-2 | I33: PO-3 | J33: PO-4 | K33: PO-5 | L33: PO-6 | P33: PO-36 | Q33: PO-10 | R33: PO-20 | S33: PO-33 | T33: PO-35 | U33: PO-32
G34: 1 | H34: 2 | I34: 3 | J34: 4 | K34: 5 | L34: 6 | P34: 10 | Q34: 11 | R34: 12 | S34: 13 | T34: 14 | U34: 15

Sheet ITK_data
A1: Action | B1: Date | C1: Produits | D1: Cibles | E1: Détails
A20: FACONS CULTURALES
A21: Date | C21: Interventions | G21: Profondeur
C22: déchaumage | G22: 10
A23: 42237 | C23: labour | G23: 25
A24: 42238 | C24: rotative croskillette | G24: 5
A25: 42247 | C25: rotative croskillette | G25: 5
A27: FICHE CULTURALE
A28: IRRIGATION
A29: Date | B29: Quantité
A30: 42257 | B30: 20
A36: FERTILISATION
A37: Date | B37: Type | C37: Quantité/ha | E37: N | F37: P0205 | G37: K2O | H37: MG0 | I37: S03
A38: 42418 | B38: N39 | C38: 230 | E38: =2.3*39 -> 89.7
A39: 42426 | B39: MAG 15-40 | C39: 150 | H39: 22.5 | I39: 60
A40: 42440 | B40: N40 | C40: 230 | E40: 89.7
A44: PROTECTION DES CULTURES
A45: Insecticides | B45: Date | C45: Produits et doses
A46: (Sol - foliaire) | B46: 42278 | C46: Karaté Xpress 0,15
B47: 42479 | C47: Mavrick 0,2
B48: 42492 | C48: Décis Protech 0,3
A51: Herbicides | B51: 42278 | C51: Novall 1,0
B52: 42298 | C52: Novall 1,0
B53: 42424 | C53: Stratos Ultra 1,5
A57: Fongicides | B57: 42481 | C57: Sunorg 0,2 + Pictor Pro 0,25
A58: + Oligo | B58: 42495 | C58: Prosaro 0,5
A63: Autres | B63: 42255 | C63: Extra lugett 5 kg
A64: (Racourcisseur, | B64: 42306 | C64: Extra lugett 5 kg
A65: anti-limaces)
